{
    "version": "https://jsonfeed.org/version/1",
    "title": "新浪新闻",
    "home_page_url": "https://tk14.github.io/sina-news/",
    "feed_url": "https://tk14.github.io/sina-news/rss.json",
    "description": "新浪全球实时财经新闻直播",
    "items": [
        {
            "id": 2302214,
            "content_html": "",
            "url": "https://finance.sina.cn/7x24/2021-09-04/detail-iktzqtyt3936320.d.html",
            "title": "  市场消息：摩根大通(JPM.N)的目标是未来10年为气候变化提供2.5万亿美元资金。",
            "date_modified": "2021-09-03T16:28:45.000Z"
        },
        {
            "id": 2302213,
            "content_html": "",
            "url": "https://finance.sina.cn/7x24/2021-09-04/detail-iktzscyx2168068.d.html",
            "title": "【北京大兴发生交通事故致20伤 大兴交通事故致29伤司机被控制】9月3日23时许，北京市大兴区官方微博发布消息：9月3日晚7点30分，大兴区北臧村镇六合庄村发生一起交通事故。截至目前，造成村内路边治丧人员20人受伤，其中，1人危重，4人重伤，15人轻伤，伤者均已送往医院救治。涉事司机马某已被公安机关控制，事故原因正在进一步调查中。（北京日报）",
            "date_modified": "2021-09-03T16:26:32.000Z"
        },
        {
            "id": 2302212,
            "content_html": "",
            "url": "https://finance.sina.cn/7x24/2021-09-04/detail-iktzqtyt3936133.d.html",
            "title": "  SEA(SE.N)涨近3%，报348.88美元，逼近历史最高价，市值逼近1900亿美元。该股年内累涨超70%，据悉，Sea的CEO李小冬登顶新加坡首富。",
            "date_modified": "2021-09-03T16:26:03.000Z"
        },
        {
            "id": 2302211,
            "content_html": "",
            "url": "https://finance.sina.cn/7x24/2021-09-04/detail-iktzqtyt3935862.d.html",
            "title": "  Truist证券：将博通(AVGO.O)目标价从554美元上调至564美元。",
            "date_modified": "2021-09-03T16:23:21.000Z"
        },
        {
            "id": 2302209,
            "content_html": "",
            "url": "https://finance.sina.cn/7x24/2021-09-04/detail-iktzqtyt3935785.d.html",
            "title": "【新疆喀什地区叶城县发生4.0级地震】中国地震台网正式测定：09月03日23时48分在新疆喀什地区叶城县（北纬37.86度，东经77.88度）发生4.0级地震，震源深度10千米。",
            "date_modified": "2021-09-03T16:22:26.000Z"
        },
        {
            "id": 2302208,
            "content_html": "",
            "url": "https://finance.sina.cn/7x24/2021-09-04/detail-iktzqtyt3935728.d.html",
            "title": "美国伊朗核谈判特使：美国不能永远等待伊朗核谈判。",
            "date_modified": "2021-09-03T16:21:47.000Z"
        },
        {
            "id": 2302207,
            "content_html": "",
            "url": "https://finance.sina.cn/7x24/2021-09-04/detail-iktzscyx2167344.d.html",
            "title": "秘鲁7月白银出口量同比增长16.79％至44万盎司。",
            "date_modified": "2021-09-03T16:19:29.000Z"
        },
        {
            "id": 2302206,
            "content_html": "",
            "url": "https://finance.sina.cn/7x24/2021-09-04/detail-iktzqtyt3935438.d.html",
            "title": "秘鲁7月的黄金出口量同比增长36.87％至46.55万盎司。",
            "date_modified": "2021-09-03T16:18:59.000Z"
        },
        {
            "id": 2302205,
            "content_html": "",
            "url": "https://finance.sina.cn/7x24/2021-09-04/detail-iktzscyx2167197.d.html",
            "title": "秘鲁7月铜出口较去年下降5.58％至18.84万吨。",
            "date_modified": "2021-09-03T16:17:47.000Z"
        },
        {
            "id": 2302204,
            "content_html": "",
            "url": "https://finance.sina.cn/7x24/2021-09-04/detail-iktzscyx2167163.d.html",
            "title": "【上半年17家公司被强制退市，23家*ST公司预警财务退市风险】2020年是退市新规执行的首个会计年度。根据新规，上市公司连续两年触及财务类指标即终止上市，因此2021年半年报也是观测上市公司退市风险的关键窗口。以半年报数据前瞻，截至2021年末，在41家沪市*ST公司中，有23家可能触及净资产为负、“净利润+营业收入组合”的财务退市指标。业内人士表示，强监管背景下，上市公司只有切实增强主营业务，提升持续经营能力，才能避免被清退。同时，投资者也要注意“炒小炒差”的风险，火中取栗要不得。（中证报）",
            "date_modified": "2021-09-03T16:17:25.000Z"
        },
        {
            "id": 2302203,
            "content_html": "",
            "url": "https://finance.sina.cn/7x24/2021-09-04/detail-iktzscyx2167118.d.html",
            "title": "【欧洲债市：德债和意债均下挫，但缩减盘中跌幅】德国国债缩减熊市趋陡走势，因股市走低。德债稍早下跌，因此前公布的美国企业盈利数据优于预期，并且下周将发行长期美国国债，非农就业数据逊于预期。 意大利国债也缩减跌幅，但跑输欧元区其它国债，Danske策略师预测下周发行30年期意大利国债，英债与美债联袂熊市趋陡；英国10年期国债收益率创下2月来最大周升幅。",
            "date_modified": "2021-09-03T16:16:52.000Z"
        },
        {
            "id": 2302202,
            "content_html": "",
            "url": "https://finance.sina.cn/7x24/2021-09-04/detail-iktzscyx2167043.d.html",
            "title": "  大华继显：将网易有道(DAO.N)评级从跑输大市上调至持有。",
            "date_modified": "2021-09-03T16:15:54.000Z"
        },
        {
            "id": 2302200,
            "content_html": "",
            "url": "https://finance.sina.cn/7x24/2021-09-04/detail-iktzscyx2166892.d.html",
            "title": "  【广州拟规定学校开门时间与上班时间挂钩】近日，《广州市学校安全管理条例》草案修改建议稿提出，将拟定学校开关门时间与市民上下班时间挂钩，开门时间不晚于市民上班前1.5小时，关闭时间不早于下班后半小时。如果以“朝九晚五”的上班族计算，学校上午开门时间应在上午7点半前，下午关闭时间要在5点半之后。",
            "date_modified": "2021-09-03T16:13:50.000Z"
        },
        {
            "id": 2302199,
            "content_html": "",
            "url": "https://finance.sina.cn/7x24/2021-09-04/detail-iktzqtyt3934609.d.html",
            "title": "  投行Evercore ISI：将DocuSign(DOCU.O)目标价从285美元上调至320美元。",
            "date_modified": "2021-09-03T16:08:43.000Z"
        },
        {
            "id": 2302198,
            "content_html": "",
            "url": "https://finance.sina.cn/7x24/2021-09-04/detail-iktzscyx2166226.d.html",
            "title": "【商务部：1-7月中非贸易额同比增长40.5%，创历史同期最高位】商务部网站9月3日消息，商务部副部长钱克明表示，1-7月，中非贸易额1391亿美元，同比增长40.5%，达到历史同期最高位。特别是中国市场对非洲产品认可度不断提高，从非洲进口同比增长了46.3%，达到593亿美元，其中橡胶、棉花、咖啡等农产品进口量较去年同期翻了一番。（人民网）",
            "date_modified": "2021-09-03T16:06:28.000Z"
        },
        {
            "id": 2302197,
            "content_html": "",
            "url": "https://finance.sina.cn/7x24/2021-09-04/detail-iktzscyx2165570.d.html",
            "title": "【雷军持股减少逾3亿股，小米：并非减持！】9月3日，港交所披露，小米集团创始人、董事长兼CEO雷军个人对小米的持股比例从10.63%降至9.12%，持股数量减少3.08亿股。小米集团公关部总经理王化在微博回应称，雷军不再控制雷军基金会导致可统计份额降低，并非减持。这家基金会是一家具有公共性质的慈善机构，而雷军根据香港当地条例终止对该基金会的控制。（中证报）",
            "date_modified": "2021-09-03T16:00:14.000Z"
        },
        {
            "id": 2302196,
            "content_html": "",
            "url": "https://finance.sina.cn/7x24/2021-09-03/detail-iktzqtyt3933434.d.html",
            "title": "【德国总理默克尔再次前往洪涝灾区 承诺将继续提供必要支持】当地时间9月3日，德国总理默克尔再次前往莱茵兰-普法尔茨州的阿尔河流域洪涝灾区进行视察。她在走访并了解了灾区清理工作的进展后承诺，联邦政府将继续提供必要的支持。",
            "date_modified": "2021-09-03T15:56:10.000Z"
        },
        {
            "id": 2302193,
            "content_html": "",
            "url": "https://finance.sina.cn/7x24/2021-09-03/detail-iktzscyx2165052.d.html",
            "title": "中国地震台网自动测定：09月03日23时48分在新疆和田地区皮山县附近发生4.3级左右地震，最终结果以正式速报为准。",
            "date_modified": "2021-09-03T15:52:00.000Z"
        },
        {
            "id": 2302192,
            "content_html": "",
            "url": "https://finance.sina.cn/7x24/2021-09-03/detail-iktzscyx2164718.d.html",
            "title": "  C3.ai(AI.N)短线发力，涨近8%，现报51.45美元，昨日公司在公布财报后收跌超10%。",
            "date_modified": "2021-09-03T15:47:51.000Z"
        },
        {
            "id": 2302189,
            "content_html": "",
            "url": "https://finance.sina.cn/7x24/2021-09-03/detail-iktzqtyt3932542.d.html",
            "title": "市场消息：美国民主党人提出法案，将把联邦医疗保险的资格降低到60岁。",
            "date_modified": "2021-09-03T15:42:44.000Z"
        },
        {
            "id": 2302186,
            "content_html": "",
            "url": "https://finance.sina.cn/7x24/2021-09-03/detail-iktzscyx2164105.d.html",
            "title": "市场消息：美国国防部长奥斯汀将访问包括卡塔尔和科威特在内的中东盟国。",
            "date_modified": "2021-09-03T15:38:09.000Z"
        },
        {
            "id": 2302185,
            "content_html": "",
            "url": "https://finance.sina.cn/7x24/2021-09-03/detail-iktzscyx2164025.d.html",
            "title": "【北约秘书长：欧盟欲创建的快速反应部队不能取代北约】北约秘书长斯托尔滕贝格当地时间9月3日表示，他支持欧盟创建一支快速反应部队的计划，但该军事力量不能占用北约的资源，也不能取代北约。",
            "date_modified": "2021-09-03T15:36:36.000Z"
        },
        {
            "id": 2302184,
            "content_html": "",
            "url": "https://finance.sina.cn/7x24/2021-09-03/detail-iktzscyx2163965.d.html",
            "title": "高盛集团大宗商品研究全球主管Jeff Currie：预计布伦特原油价格到2021年年底将涨至80美元/桶，如果一系列因素整体表现适当，油价甚至会突破该价位。",
            "date_modified": "2021-09-03T15:35:42.000Z"
        },
        {
            "id": 2302183,
            "content_html": "",
            "url": "https://finance.sina.cn/7x24/2021-09-03/detail-iktzqtyt3931915.d.html",
            "title": "【西班牙前国王胡安·卡洛斯回应涉嫌洗钱：相关指控没有根据】根据西班牙媒体当地时间9月3日的报道，在西班牙最高法院检察官办公室表示将对西班牙前国王胡安·卡洛斯一世涉嫌洗钱等多项罪名展开调查后，胡安·卡洛斯一世通过其辩护律师发布声明称，检察官办公室对于他的罪名指控没有根据。",
            "date_modified": "2021-09-03T15:33:10.000Z"
        },
        {
            "id": 2302174,
            "content_html": "",
            "url": "https://finance.sina.cn/7x24/2021-09-03/detail-iktzscyx2162715.d.html",
            "title": "【德国法院再次驳回德国铁路公司要求禁止工会罢工的申诉】德国黑森州地方劳动法院当地时间9月3日驳回了德国铁路公司提出的禁止火车司机工会罢工的申诉。这意味着德国火车司机工会的罢工将按原计划持续到9月7日凌晨。德国铁路公司对法院的裁决表示遗憾。（央视）",
            "date_modified": "2021-09-03T15:18:34.000Z"
        },
        {
            "id": 2302173,
            "content_html": "",
            "url": "https://finance.sina.cn/7x24/2021-09-03/detail-iktzscyx2162507.d.html",
            "title": "WhatsApp爱尔兰分公司周四因未能达到欧盟通用数据保护条例（GDPR）标准而面临2.67亿美元的巨额罚款，但这并不是GDPR历史的最大一笔罚金。数据显示，在最高罚款名单上排名第一的是亚马逊，该公司欧洲分支机构于今年7月份因“不遵守一般数据处理原则”遭罚8.86亿美元，第三名是谷歌，其次是瑞典时装公司H&M和意大利电信提供商TIM。",
            "date_modified": "2021-09-03T15:15:34.000Z"
        },
        {
            "id": 2302171,
            "content_html": "",
            "url": "https://finance.sina.cn/7x24/2021-09-03/detail-iktzqtyt3930642.d.html",
            "title": "市场消息：美国总统拜登助手对停止失业救济的影响感到担忧。",
            "date_modified": "2021-09-03T15:15:18.000Z"
        },
        {
            "id": 2302167,
            "content_html": "",
            "url": "https://finance.sina.cn/7x24/2021-09-03/detail-iktzqtyt3930176.d.html",
            "title": "市场消息：美国军事基地可以容纳36000名阿富汗难民。",
            "date_modified": "2021-09-03T15:09:57.000Z"
        },
        {
            "id": 2302156,
            "content_html": "",
            "url": "https://finance.sina.cn/7x24/2021-09-03/detail-iktzscyx2161272.d.html",
            "title": "数据显示，纽约周三晚间的暴雨打破了该地区之前的降水纪录，9月1日晚8:51到9:51期间，纽约中央公园ASOS（自动地面观测系统）记录了3.15英寸的降雨，打破了11天前由飓风“亨利”创造的纪录。纽约此次强降雨系飓风“艾达”的余威造成，美国东北部地区普遍受到此次强降雨影响。",
            "date_modified": "2021-09-03T15:01:37.000Z"
        },
        {
            "id": 2302153,
            "content_html": "",
            "url": "https://finance.sina.cn/7x24/2021-09-03/detail-iktzqtyt3929230.d.html",
            "title": "美国总统拜登：国会需要完成他们在经济计划方面的工作。",
            "date_modified": "2021-09-03T14:59:16.000Z"
        },
        {
            "id": 2302152,
            "content_html": "",
            "url": "https://finance.sina.cn/7x24/2021-09-03/detail-iktzqtyt3929203.d.html",
            "title": "美国总统拜登：是时候给工薪家庭减税了。",
            "date_modified": "2021-09-03T14:58:52.000Z"
        },
        {
            "id": 2302151,
            "content_html": "",
            "url": "https://finance.sina.cn/7x24/2021-09-03/detail-iktzscyx2161042.d.html",
            "title": "印度修订汽车激励计划，重点关注电动汽车和氢能源汽车。",
            "date_modified": "2021-09-03T14:58:43.000Z"
        },
        {
            "id": 2302149,
            "content_html": "",
            "url": "https://finance.sina.cn/7x24/2021-09-03/detail-iktzscyx2160839.d.html",
            "title": "Moderna(MRNA.O)短线下挫，现跌0.7%。",
            "date_modified": "2021-09-03T14:56:27.000Z"
        },
        {
            "id": 2302148,
            "content_html": "",
            "url": "https://finance.sina.cn/7x24/2021-09-03/detail-iktzqtyt3928982.d.html",
            "title": "市场消息：官员们可能会在接下来几周建议接种辉瑞加强剂。",
            "date_modified": "2021-09-03T14:56:08.000Z"
        },
        {
            "id": 2302147,
            "content_html": "",
            "url": "https://finance.sina.cn/7x24/2021-09-03/detail-iktzqtyt3928910.d.html",
            "title": "中概股网易有道涨9.2%，掌门教育涨超4.0%，B站涨3.1%，新东方涨3.0%，第一高中教育集团涨超2.8%，高途教育涨2.6%，腾讯音乐涨2.1%，精锐教育则跌2.6%，水滴跌2.7%，涂鸦智能跌3.2%，一起教育跌3.5%，乐居跌4.0%，容联云跌4.6%，贝克找房跌5.8%。",
            "date_modified": "2021-09-03T14:55:24.000Z"
        },
        {
            "id": 2302146,
            "content_html": "",
            "url": "https://finance.sina.cn/7x24/2021-09-03/detail-iktzqtyt3928783.d.html",
            "title": "市场消息：有官员建议白宫缩减刺激计划规模。",
            "date_modified": "2021-09-03T14:53:43.000Z"
        },
        {
            "id": 2302145,
            "content_html": "",
            "url": "https://finance.sina.cn/7x24/2021-09-03/detail-iktzscyx2160297.d.html",
            "title": "美国联邦应急管理署（FEMA）表示，总统拜登批准了新泽西州的紧急状态声明。",
            "date_modified": "2021-09-03T14:50:15.000Z"
        },
        {
            "id": 2302144,
            "content_html": "",
            "url": "https://finance.sina.cn/7x24/2021-09-03/detail-iktzqtyt3928360.d.html",
            "title": "美国国家飓风中心：风暴“拉里”似乎准备进一步加强。",
            "date_modified": "2021-09-03T14:49:39.000Z"
        },
        {
            "id": 2302143,
            "content_html": "",
            "url": "https://finance.sina.cn/7x24/2021-09-03/detail-iktzqtyt3928347.d.html",
            "title": "美国总统拜登：国会在9月份通过我的经济议程非常重要。",
            "date_modified": "2021-09-03T14:49:33.000Z"
        },
        {
            "id": 2302142,
            "content_html": "",
            "url": "https://finance.sina.cn/7x24/2021-09-03/detail-iktzscyx2160066.d.html",
            "title": "美国总统拜登：下周将采取更多措施打击德尔塔变种毒株。",
            "date_modified": "2021-09-03T14:47:55.000Z"
        },
        {
            "id": 2302141,
            "content_html": "",
            "url": "https://finance.sina.cn/7x24/2021-09-03/detail-iktzscyx2160022.d.html",
            "title": "美国总统拜登：就业报告并不那么强劲。",
            "date_modified": "2021-09-03T14:47:16.000Z"
        },
        {
            "id": 2302138,
            "content_html": "",
            "url": "https://finance.sina.cn/7x24/2021-09-03/detail-iktzqtyt3927918.d.html",
            "title": "美国总统拜登：需要持续创造就业。",
            "date_modified": "2021-09-03T14:43:25.000Z"
        },
        {
            "id": 2302137,
            "content_html": "",
            "url": "https://finance.sina.cn/7x24/2021-09-03/detail-iktzqtyt3927826.d.html",
            "title": "美国总统拜登：美国经济复苏是持久和强劲的。",
            "date_modified": "2021-09-03T14:42:28.000Z"
        },
        {
            "id": 2302134,
            "content_html": "",
            "url": "https://finance.sina.cn/7x24/2021-09-03/detail-iktzscyx2159610.d.html",
            "title": "  医药器材公司Cellect Biotechnology(APOP.O)异动走高，现涨超40%，今日公司宣布使用其产品ApoGraft进行的骨髓移植试验顺利完成。",
            "date_modified": "2021-09-03T14:41:31.000Z"
        },
        {
            "id": 2302133,
            "content_html": "",
            "url": "https://finance.sina.cn/7x24/2021-09-03/detail-iktzscyx2159366.d.html",
            "title": "美国汽车销量在8月份暴跌至调整后的年化1309万辆，创2020年6月来最低。销量下滑的主要原因是汽车库存水平持续下滑。",
            "date_modified": "2021-09-03T14:40:09.000Z"
        },
        {
            "id": 2302129,
            "content_html": "",
            "url": "https://finance.sina.cn/7x24/2021-09-03/detail-iktzqtyt3926900.d.html",
            "title": "中国恒大：2021年1月份至8月份，本集团物业累计实现合约销售金额4,386.5亿元人民币，合约销售面积5,379.0万平方米。",
            "date_modified": "2021-09-03T14:32:51.000Z"
        },
        {
            "id": 2302125,
            "content_html": "",
            "url": "https://finance.sina.cn/7x24/2021-09-03/detail-iktzqtyt3926726.d.html",
            "title": "  市场消息：巴克莱(BCS.N)计划重回碳积分与碳排放交易业务。",
            "date_modified": "2021-09-03T14:30:48.000Z"
        },
        {
            "id": 2302120,
            "content_html": "",
            "url": "https://finance.sina.cn/7x24/2021-09-03/detail-iktzqtyt3925575.d.html",
            "title": "  【深圳“双减”：全面深入开展为期一个月的联合执法检查】深圳于近日印发《关于开展减轻义务教育阶段学生校外培训负担联合执法检查行动的通知》，开展为期一个月的全市减轻义务教育阶段学生校外培训负担联合执法检查。强化依法执法、文明执法、市区联动，分别成立由教育行政部门联合市场监管、城管和综合执法、卫健、公安、消防救援等部门组成的检查组，检查对象主要为面向义务教育阶段中小学生及幼儿园儿童举办的学科类及体育、文化艺术、科技等非学科类校外培训机构。",
            "date_modified": "2021-09-03T14:19:25.000Z"
        },
        {
            "id": 2302117,
            "content_html": "",
            "url": "https://finance.sina.cn/7x24/2021-09-03/detail-iktzqtyt3925283.d.html",
            "title": "  亿航智能(EH.O)早盘一度涨超7%，现回落至5%，今日公司宣布旗舰产品载人级自动驾驶飞行器亿航216和天鹰物流机在爱沙尼亚完成超视距飞行测试。",
            "date_modified": "2021-09-03T14:15:39.000Z"
        },
        {
            "id": 2302116,
            "content_html": "",
            "url": "https://finance.sina.cn/7x24/2021-09-03/detail-iktzscyx2157098.d.html",
            "title": "  【上海持续推进700MHz频段5G网络建设 预计年底建成4000个700M基站】今日下午，上海市经济信息化委副主任张建明赴临港调研700MHz频段5G网络建设。据悉，随着700M 5G网络建设加速，预计2021年底，上海市建成4000个700M基站，2022年累计建成8000个700M基站。",
            "date_modified": "2021-09-03T14:15:31.000Z"
        }
    ]
}