{
    "version": "https://jsonfeed.org/version/1",
    "title": "新浪新闻",
    "home_page_url": "https://tk14.github.io/sina-news/",
    "feed_url": "https://tk14.github.io/sina-news/rss.json",
    "description": "新浪全球实时财经新闻直播",
    "items": [
        {
            "id": 3681666,
            "content_html": "",
            "url": "https://finance.sina.cn/7x24/2024-07-04/detail-incaxnrt5571960.d.html",
            "title": "【自然资源部与中国气象局7月4日08时联合发布地质灾害气象风险预警】自然资源部与中国气象局7月4日08时联合发布地质灾害气象风险预警：预计，7月4日08时至5日08时，湖北西部、四川东北部、云南西北部、西藏东南部、陕西南部等地的部分地区发生地质灾害的风险较高（黄色预警）。请当地居民注意防范降水引发的地质灾害，尤其是地质灾害隐患点附近区域。",
            "date_modified": "2024-07-04T01:01:17.000Z"
        },
        {
            "id": 3681661,
            "content_html": "",
            "url": "https://finance.sina.cn/7x24/2024-07-04/detail-incaxnrt5571525.d.html",
            "title": "【安徽马鞍山将防汛应急响应提升至二级】 7月4日，马鞍山市防汛抗旱指挥部发布关于将防汛应急响应提升至二级的通知。",
            "date_modified": "2024-07-04T00:59:39.000Z"
        },
        {
            "id": 3681660,
            "content_html": "",
            "url": "https://finance.sina.cn/7x24/2024-07-04/detail-incaxnru7686269.d.html",
            "title": "市场消息：美国广播公司对拜登的采访将于美国东部时间周五晚上8点（北京时间次日早上8点）播出。",
            "date_modified": "2024-07-04T00:56:22.000Z"
        },
        {
            "id": 3681659,
            "content_html": "",
            "url": "https://finance.sina.cn/7x24/2024-07-04/detail-incaxnru7686157.d.html",
            "title": "【美媒：阿肯色州一家武器工厂发生爆炸，致2人受伤、1人失踪】 据美联社当地时间7月3日报道，阿肯色州一家国防武器工厂当天发生爆炸，造成至少2人受伤、1人失踪。",
            "date_modified": "2024-07-04T00:56:01.000Z"
        },
        {
            "id": 3681656,
            "content_html": "",
            "url": "https://finance.sina.cn/7x24/2024-07-04/detail-incaxnrt5570481.d.html",
            "title": "宋都服务7月4日在港交所公告，公司股份将于今天7月4日上午九时正起恢复买卖。",
            "date_modified": "2024-07-04T00:53:47.000Z"
        },
        {
            "id": 3681655,
            "content_html": "",
            "url": "https://finance.sina.cn/7x24/2024-07-04/detail-incaxnrp6073491.d.html",
            "title": "【电动汽车增长放缓，巴斯夫据悉终止智利投资计划】 由于全球电动汽车应用放缓拖累了电池金属价格，德国化学品制造商巴斯夫表示，该公司放弃了在智利投资锂矿资产的计划，退出了与总部位于温哥华、在智利拥有勘探项目的公司Wealth Minerals Ltd. 的初步谈判。",
            "date_modified": "2024-07-04T00:53:38.000Z"
        },
        {
            "id": 3681654,
            "content_html": "",
            "url": "https://finance.sina.cn/7x24/2024-07-04/detail-incaxnrp6073266.d.html",
            "title": "【全球基金买入泰国股票触及1个月高点】泰国债券市场协会数据显示，7月3日国际基金净卖出9,780万美元泰国债券，连续第六天遭到抛售。据交易所数据，7月3日全球基金净买入3,600万美元该国股票，为5月16日来最高。",
            "date_modified": "2024-07-04T00:53:08.000Z"
        },
        {
            "id": 3681652,
            "content_html": "",
            "title": "特斯拉(TSLA.O)今日宣布Model 3上线全新车漆“快银”，特斯拉中国官网显示选配价格为12000元。",
            "date_modified": "2024-07-04T00:50:25.000Z"
        },
        {
            "id": 3681651,
            "content_html": "",
            "url": "https://finance.sina.cn/7x24/2024-07-04/detail-incaxnru7683006.d.html",
            "title": "【江苏发布强对流黄色预警】江苏省气象台2024年07月04日07时32分发布强对流黄色预警： 预计今天白天，宿迁、淮安、盐城、连云港、扬州北部等地的部分地区将出现8-10级雷暴大风，局地可达11级。",
            "date_modified": "2024-07-04T00:48:37.000Z"
        },
        {
            "id": 3681649,
            "content_html": "",
            "url": "https://finance.sina.cn/7x24/2024-07-04/detail-incaxnrp6070503.d.html",
            "title": "【深交所：华夏深国际仓储物流封闭式基础设施证券投资基金上市交易】 深交所公告，华夏深国际仓储物流封闭式基础设施证券投资基金（证券简称：华夏深国际REIT，证券代码：180302)自2024年7月9日起在本所上市交易。",
            "date_modified": "2024-07-04T00:47:18.000Z"
        },
        {
            "id": 3681648,
            "content_html": "",
            "url": "https://finance.sina.cn/7x24/2024-07-04/detail-incaxnrp6070396.d.html",
            "title": "澳大利亚10年期实际收益率跌1.4个基点至1.94%。",
            "date_modified": "2024-07-04T00:47:05.000Z"
        },
        {
            "id": 3681647,
            "content_html": "",
            "url": "https://finance.sina.cn/7x24/2024-07-04/detail-incaxnrt5568495.d.html",
            "title": "【深房中协：6月深圳二手房交易量创近40个月新高】7月3日，深圳市房地产中介协会（“深房中协”）数据显示， 6月，深圳二手房签约量达5309套，环比增长9%，同比增长66.3%，月度二手房交易量创近40个月新高。上半年，在持续不断的楼市优化政策加持下，深圳二手房市场在春节假期返工后呈现良好走势，其中3月和6月二手房交易量突破5000套水平。另据统计，2024年上半年二手房买卖合同共计录得26,864套，较2023年下半年增长23.7%，同比2023年上半年增长28.8%。",
            "date_modified": "2024-07-04T00:46:26.000Z"
        },
        {
            "id": 3681645,
            "content_html": "",
            "url": "https://finance.sina.cn/7x24/2024-07-04/detail-incaxnrp6069811.d.html",
            "title": "香港银行向金管局贴现窗借取10亿港元隔夜流动性，为本月首次。",
            "date_modified": "2024-07-04T00:45:51.000Z"
        },
        {
            "id": 3681643,
            "content_html": "",
            "url": "https://finance.sina.cn/7x24/2024-07-04/detail-incaxnru7680998.d.html",
            "title": "韩国KOSPI指数上涨1%至2,822.90点。",
            "date_modified": "2024-07-04T00:44:03.000Z"
        },
        {
            "id": 3681640,
            "content_html": "",
            "title": "摩根士丹利表示，宁德时代3%的分红率应该会为其股价提供保护，尽管其股价最近因地缘政治和保护主义担忧而下跌；维持对公司的增持评级，目标价230元。",
            "date_modified": "2024-07-04T00:42:28.000Z"
        },
        {
            "id": 3681638,
            "content_html": "",
            "title": "比亚迪汽车：10万级混动SUV冠军 宋Pro DM-i荣耀版 6月热销20330辆。",
            "date_modified": "2024-07-04T00:39:46.000Z"
        },
        {
            "id": 3681637,
            "content_html": "",
            "url": "https://finance.sina.cn/7x24/2024-07-04/detail-incaxnru7679020.d.html",
            "title": "【河南山东等地有较强降雨 南方高温闷热天气加强】随着副热带高压西伸北抬，今起三天（7月4日至6日），主雨带将从前期的长江中下游地区北抬至黄淮地区，河南、山东、河北南部和东部等地将出现大雨或暴雨，部分地区有大暴雨。同时，在副热带高压的控制下，江南、华南等地高温闷热天气盛行。北方大部虽然高温天气减弱，但黑龙江西北部或现同期少见高温。",
            "date_modified": "2024-07-04T00:39:30.000Z"
        },
        {
            "id": 3681635,
            "content_html": "",
            "url": "https://finance.sina.cn/7x24/2024-07-04/detail-incaxnrt5565749.d.html",
            "title": "【阿联酋300亿美元气候投资基金准备下一轮投资】 阿拉伯联合酋长国出资300亿美元成立的Alterra气候投资基金正在准备下一轮投资，该基金宣称其目标是为气候融资注入数十亿美元。Alterra基金首席执行官马吉德·苏韦迪表示，该基金去年底与贝莱德、TPG公司和布鲁克菲尔德资产管理公司达成了价值65亿美元的交易。",
            "date_modified": "2024-07-04T00:35:21.000Z"
        },
        {
            "id": 3681634,
            "content_html": "",
            "url": "https://finance.sina.cn/7x24/2024-07-04/detail-incaxnrt5565681.d.html",
            "title": "【继《纽约时报》后，美国《波士顿环球报》也发社评呼吁拜登“优雅退选”】 美国《波士顿环球报》当地时间7月3日也发社评，敦促拜登退出总统竞选，理由是，拜登上星期在辩论中的“历史性糟糕表现”没得到充分解释。",
            "date_modified": "2024-07-04T00:34:54.000Z"
        },
        {
            "id": 3681633,
            "content_html": "",
            "url": "https://finance.sina.cn/7x24/2024-07-04/detail-incaxnrp6064030.d.html",
            "title": "【中信证券：下半年新型烟草行业增长预期料将改善】中信证券研报指出，2024年5月至6月全球新型烟草市场情况较为正面：一方面美国监管频频释放积极信号，另一方面2024年5月中国电子烟出口额10.1亿美元，同比增速转正；HNB核心市场日本和德国需求保持快速增长。传统烟草方面，随着出境游需求复苏和中烟集团拓展海外市场进程，中国卷烟出口延续高增，烟叶进口数量创新高，烟叶出口均价大幅增长。2024年全球经济面临不确定性，烟草行业体现刚性需求特征。鉴于美国电子烟监管政策频频释放积极信号，菲莫国际与英美烟草也在HNB产品上达成专利和解，下半年新型烟草行业增长预期料将改善。",
            "date_modified": "2024-07-04T00:31:27.000Z"
        },
        {
            "id": 3681632,
            "content_html": "",
            "url": "https://finance.sina.cn/7x24/2024-07-04/detail-incaxnrp6063565.d.html",
            "title": "市场消息：一些民主党代表希望在拜登获得提名前能有更多时间。",
            "date_modified": "2024-07-04T00:30:17.000Z"
        },
        {
            "id": 3681631,
            "content_html": "",
            "url": "https://finance.sina.cn/7x24/2024-07-04/detail-incaxnru7674809.d.html",
            "title": "【铠侠产能满载 传7月量产最先进NAND Flash产品】铠侠产线稼动率据悉已在6月回升至100%水准、且将在7月内量产最先进存储芯片(NAND Flash)产品，借此开拓因生成式AI普及而急增的数据存储需求。据悉，铠侠将开始量产的NAND Flash产品堆叠218层数据存储元件，和现行产品相比，存储容量提高约50%，写入数据时所需的电力缩减约30%。 (MoneyDJ)",
            "date_modified": "2024-07-04T00:28:05.000Z"
        },
        {
            "id": 3681625,
            "content_html": "",
            "url": "https://finance.sina.cn/7x24/2024-07-04/detail-incaxnrp6061209.d.html",
            "title": "【AI需求推动存储芯片价格反弹 分析师预计三星电子第二季度利润将同比增长12倍】由于对人工智能(AI)技术的需求推动了存储芯片价格的反弹，预计三星电子第二季度的利润将同比增长12倍。根据LSEG SmartEstimate统计的27位分析师预估均值显示，三星电子在截至6月30日当季的营业利润可能增至8.8万亿韩元(63.4亿美元)。",
            "date_modified": "2024-07-04T00:23:34.000Z"
        },
        {
            "id": 3681624,
            "content_html": "",
            "url": "https://finance.sina.cn/7x24/2024-07-04/detail-incaxnru7672942.d.html",
            "title": "【阳光慧碳携手意法半导体 探索ST及其供应链全球减碳举措】 阳光电源旗下的高新技术企业阳光慧碳与全球排名前列的半导体公司意法半导体（简称ST）签署了一项广泛的合作协议，共同推动全球范围内ST及其供应链的减碳行动。双方将探索多种潜在的合作方式，包括在产品和系统层面的碳足迹核算，内部碳定价，在ST的设施内部署产品和解决方案，以及开展一个潜在的试点项目等。这一合作，也标志着慧碳方案迈出了“出海”第一步。",
            "date_modified": "2024-07-04T00:23:23.000Z"
        },
        {
            "id": 3681622,
            "content_html": "",
            "url": "https://finance.sina.cn/7x24/2024-07-04/detail-incaxnru7672419.d.html",
            "title": "【被问拜登是否考虑退选，白宫新闻秘书：他绝对不会考虑】 白宫新闻秘书卡里娜·让-皮埃尔当地时间7月3日在记者会上称，拜登“绝对不会”考虑退出竞选。（环球网）",
            "date_modified": "2024-07-04T00:22:09.000Z"
        },
        {
            "id": 3681621,
            "content_html": "",
            "url": "https://finance.sina.cn/7x24/2024-07-04/detail-incaxnru7672262.d.html",
            "title": "【注意防范！广西东兴更新暴雨红色预警信号】 广西东兴市气象台2024年7月4日5时37分将暴雨橙色预警信号提升为红色：过去3小时竹围村已出现110毫米以上强降水，目前仍有强降雨云团从海面持续北上影响东兴市，预计未来3小时，东兴镇、马路镇、江平镇仍有40—80毫米的强降雨，并伴有雷电或大风，请注意防范。1、政府及相关部门按照职责做好防暴雨应急和抢险工作；2、停止集会、停课、停业（除特殊行业外）；3、做好山洪、滑坡、泥石流等灾害的防御和抢险工作。",
            "date_modified": "2024-07-04T00:21:44.000Z"
        },
        {
            "id": 3681620,
            "content_html": "",
            "title": "【“海安2024”渤海海域联合巡航执法行动启动】 7月3日，为期三天的“海安2024”渤海海域联合巡航执法行动在沧州海域启动。河北、山东、天津、辽宁四地海事部门联合海警、海监、渔政等单位在渤海海域共同开展内河船非法涉海运输治理、船舶防污染专项整治等，以及在商渔船易发碰撞风险提示区进行巡航执法，确保水上通行安全。（新华社）",
            "date_modified": "2024-07-04T00:19:13.000Z"
        },
        {
            "id": 3681618,
            "content_html": "",
            "url": "https://finance.sina.cn/7x24/2024-07-04/detail-incaxnrp6058917.d.html",
            "title": "软银将优先考虑人工智能交易而不是股票回购。目前软银没有立即回购股票的计划。",
            "date_modified": "2024-07-04T00:18:26.000Z"
        },
        {
            "id": 3681616,
            "content_html": "",
            "url": "https://finance.sina.cn/7x24/2024-07-04/detail-incaxnrp6058365.d.html",
            "title": "【江西新余：2026年底实现“保交楼”“保交房”项目全面清零】 新余市发布《新余市房地产业高质量发展三年行动方案（2024-2026）》。其中提到，制定出台消化存量房产的政策措施，实现本市商品房销售企稳回升，商品住房去化周期在2024年底缩短至30个月，2025年底缩短至24个月，至2026年缩短至18个月的正常区间范围以内，商品房销售面积增幅达到全省平均水平以上。杜绝新增烂尾。2026年底实现“保交楼”“保交房”项目全面清零，保障购房人合法权益。新余市还提出，开展多种“以旧换新”模式。",
            "date_modified": "2024-07-04T00:16:48.000Z"
        },
        {
            "id": 3681611,
            "content_html": "",
            "url": "https://finance.sina.cn/7x24/2024-07-04/detail-incaxnru7669484.d.html",
            "title": "美国总统拜登及其竞选团队表示，拜登决心在投票中击败特朗普。",
            "date_modified": "2024-07-04T00:14:18.000Z"
        },
        {
            "id": 3681610,
            "content_html": "",
            "url": "https://finance.sina.cn/7x24/2024-07-04/detail-incaxnrr8783838.d.html",
            "title": "【久其软件：新一轮财税改革会有一定的市场机会】 久其软件(002279)在机构调研时表示，新一轮财税改革无论是对政府侧还是企业侧客户的信息化需求，都是持续且较为长久的，具体市场规模尚不好预计。另外，对于数字财政综合服务供应商而言，在预算一体化深入实施、财税改革会计电子标准信息化、财会监督与内部控制管理制度体系建设等方面，会有一定的市场机会。",
            "date_modified": "2024-07-04T00:12:53.000Z"
        },
        {
            "id": 3681609,
            "content_html": "",
            "url": "https://finance.sina.cn/7x24/2024-07-04/detail-incaxnru7668983.d.html",
            "title": "【宝武镁业与苏州汇川联合动力共同发布镁合金轻量化新品】 宝武镁业消息，7月3日，在中国国际铝工业展览会宝武镁业展台上，一款全球领先应用的镁合金轻量化新品——镁合金轻量化电驱总成由宝武镁业与苏州汇川联合动力系统股份有限公司共同发布。此次发布的镁合金轻量化电驱产品重量与传统铝合金材料结构相比减重2.5-7千克。同时，该产品还可以提升电机功率密度，通过材料自身吸振性，改善整车噪声、振动与声振粗糙度，并有助于优化车辆的前后配重比，改善车辆的操控性能和驾驶感受。",
            "date_modified": "2024-07-04T00:12:48.000Z"
        },
        {
            "id": 3681607,
            "content_html": "",
            "url": "https://finance.sina.cn/7x24/2024-07-04/detail-incaxnrr8783292.d.html",
            "title": "【沃尔核材：已完成多款单通道224G高速通信线样品开发】 沃尔核材(002130)在机构调研时表示，公司已完成了多款单通道224G高速通信线样品的开发，目前部分样品已通过客户的测试，小批量生产中；后续供货情况需视客户需求而定，暂未形成批量销售。",
            "date_modified": "2024-07-04T00:09:54.000Z"
        },
        {
            "id": 3681605,
            "content_html": "",
            "url": "https://finance.sina.cn/7x24/2024-07-04/detail-incaxnru7667408.d.html",
            "title": "【“关键一招”开新局 一份“独董督促函”催化上市公司治理变革】 上市公司独立董事履职正迎来新气象。随着独立董事制度改革的落地，今年以来，已有多家上市公司收到独立董事的督促函，涉及履行承诺、整改违规等多方面内容。整体来看，独立董事履职正在变得积极起来。（经济参考报）",
            "date_modified": "2024-07-04T00:08:00.000Z"
        },
        {
            "id": 3681604,
            "content_html": "",
            "url": "https://finance.sina.cn/7x24/2024-07-04/detail-incaxnru7667252.d.html",
            "title": "【印刷电路板行业发展趋势向好 多家公司透露下游需求增长】 今年以来，受益于AI服务器、5G、云计算、汽车等下游需求持续走强，PCB（印刷电路板）行业加速复苏，呈现出“淡季不淡”、行业发展趋势向好等特征。“2024年上半年，全球宏观经济温和复苏，电子信息产品市场需求改善，公司紧抓机遇，进一步提升业务开拓效率，整体业务较好增长，实现了在不同市场高效拓展以及产品份额的不断提升，客户需求旺盛，定点项目密集交付，公司整体的产能稼动率延续了增长趋势并保持较高水平。”景旺电子董秘办相关人士向记者表示。此外，深南电路近日表示，公司近期PCB工厂稼动率较2024年第一季度有所增长。胜宏科技表示，全球AI相关的PCB市场需求正在显著增长，这主要得益于算力需求不断增加和应用场景的不断扩展。",
            "date_modified": "2024-07-04T00:07:24.000Z"
        },
        {
            "id": 3681603,
            "content_html": "",
            "url": "https://finance.sina.cn/7x24/2024-07-04/detail-incaxnrp6055329.d.html",
            "title": "【通威与Colibri Capital Ltda签署合作协议】 7月2日，通威股份与巴西知名企业Colibri Capital Ltda（简称Colibri集团）正式签署合作协议，进一步加强双方在新能源领域的合作。通过此次合作，通威将成为Colibri集团公司目前的独家组件供应商。Colibri集团主营业务涵盖农业、教育、矿泉水、港口运行和太阳能业务。",
            "date_modified": "2024-07-04T00:06:56.000Z"
        },
        {
            "id": 3681602,
            "content_html": "",
            "url": "https://finance.sina.cn/7x24/2024-07-04/detail-incaxnrp6054570.d.html",
            "title": "【巴西政府公布创纪录的农业信贷计划】 巴西总统卢拉当地时间7月3日表示，他的政府将继续致力于承担财政责任，尽管他也承诺维持向符合条件的贫困家庭发放现金的政策。“财政责任不仅仅是一个词，它是对本届政府的承诺。“卢拉在一次启动家庭农业补助计划的活动中说。当天巴西雷亚尔兑美元涨超2%。当天公布的数据显示，巴西6月外汇净流入为58亿美元，高于去年同期的29亿美元。",
            "date_modified": "2024-07-04T00:04:15.000Z"
        },
        {
            "id": 3681601,
            "content_html": "",
            "url": "https://finance.sina.cn/7x24/2024-07-04/detail-incaxnrp6054456.d.html",
            "title": "【日本雅马哈股价创下1,553日元的纪录高位】 雅马哈触及1,553日元的纪录高位，上涨1.67%。该股今年迄今上涨23%，东证股价上涨21.4%。",
            "date_modified": "2024-07-04T00:03:44.000Z"
        },
        {
            "id": 3681599,
            "content_html": "",
            "url": "https://finance.sina.cn/7x24/2024-07-04/detail-incaxnrp6053952.d.html",
            "title": "【券商上半年百强营业部榜单出炉 前十强成交均超百亿元】券商营业部龙虎榜是反映市场交易情况的重要窗口，其排名情况一直备受市场关注。今年上半年，券商营业部龙虎榜排名经历了一场大“洗牌”，榜首位置由去年末的中金公司上海分公司变为东方财富拉萨金融城南环路营业部。龙虎榜成交额前一百名的营业部（简称“百强营业部”）中，有41家营业部为新上榜成员，不少中小券商“黑马”营业部涌现。从成交金额来看，前十强营业部上半年的成交金额均超过100亿元。从前十强营业部的偏好个股和题材方面来看，今年上半年，主要集中在通用设备、专用设备、汽车、计算机软件和化学制品领域。",
            "date_modified": "2024-07-04T00:02:33.000Z"
        },
        {
            "id": 3681597,
            "content_html": "",
            "url": "https://finance.sina.cn/7x24/2024-07-04/detail-incaxnrr8781254.d.html",
            "title": "【日韩股市高开】日经225指数开盘上涨0.4%，至40,747.59点；东证指数开盘上涨0.3%，至2,881.10点。韩国KOSPI指数开盘上涨0.8%，至2,817.06点。",
            "date_modified": "2024-07-04T00:00:22.000Z"
        },
        {
            "id": 3681596,
            "content_html": "",
            "title": "【隆基全球分布式研发中心落户嘉兴】 7月3日，隆基全球分布式研发中心启用仪式暨合作伙伴共创大会在嘉兴举行。全球分布式研发中心的投入使用，不仅是隆基“提升产品力”战略取得的阶段性成果，也是隆基进一步构筑BC生态链的重要里程碑。",
            "date_modified": "2024-07-03T23:57:32.000Z"
        },
        {
            "id": 3681595,
            "content_html": "",
            "title": "美国国家飓风中心表示，飓风“贝丽尔”在大开曼岛东南偏东约215英里（350公里）处，最大持续风速为每小时215公里（130英里）。",
            "date_modified": "2024-07-03T23:57:23.000Z"
        },
        {
            "id": 3681593,
            "content_html": "",
            "title": "美国国家飓风中心（NHC）表示，极度危险的4级飓风  “贝丽尔”  正在牙买加西南部附近移动，预计今晚晚些时候将接近开曼群岛。",
            "date_modified": "2024-07-03T23:56:18.000Z"
        },
        {
            "id": 3681592,
            "content_html": "",
            "title": "明尼苏达州州长沃尔兹：拜登适合担任总统；我们追求胜利之路，拜登先生也同意。",
            "date_modified": "2024-07-03T23:53:56.000Z"
        },
        {
            "id": 3681591,
            "content_html": "",
            "url": "https://finance.sina.cn/7x24/2024-07-04/detail-incaxnrp6051482.d.html",
            "title": "马里兰州州长穆尔：民主党州长们说他们会支持拜登。",
            "date_modified": "2024-07-03T23:53:10.000Z"
        },
        {
            "id": 3681590,
            "content_html": "",
            "url": "https://finance.sina.cn/7x24/2024-07-04/detail-incaxnru7663190.d.html",
            "title": "明尼苏达州州长蒂姆·沃尔兹：与美国总统拜登进行了坦诚和开放的谈话，将支持拜登竞选。",
            "date_modified": "2024-07-03T23:52:44.000Z"
        },
        {
            "id": 3681588,
            "content_html": "",
            "url": "https://finance.sina.cn/7x24/2024-07-04/detail-incaxnru7662450.d.html",
            "title": "【本田和日产考虑联合开发汽车操作系统】本田汽车 和 日产汽车正在考虑联合开发一种新的车载操作系统。新的操作系统将集成一些控制装置并标准化加速器、刹车和驾驶辅助等设备的连接。两家公司3月份同意在电动汽车等领域展开合作。（环球市场播报）",
            "date_modified": "2024-07-03T23:50:06.000Z"
        },
        {
            "id": 3681584,
            "content_html": "",
            "title": "市场消息：日本首相岸田文雄在为下周在美国举行的北约会议期间与韩国、澳大利亚和新西兰领导人举行四边峰会做准备。",
            "date_modified": "2024-07-03T23:46:53.000Z"
        },
        {
            "id": 3681583,
            "content_html": "",
            "url": "https://finance.sina.cn/7x24/2024-07-04/detail-incaxnru7661413.d.html",
            "title": "【“木头姐”旗下ETF于9个月来首次抛售特斯拉股票】  最新公布的资料显示，当地时间7月2日，绰号“木头姐”的著名基金经理凯茜·伍德领导的方舟投资对其投资组合实施重大调整，旗下两只ETF——ARKK和ARKW分别减持特斯拉56,425股和6,442股，价值约1454万美元。其中这是ARKK自去年10月以来首次出售特斯拉股票。7月3日，特斯拉股价连续第七天上涨，创一年来最长连涨纪录。",
            "date_modified": "2024-07-03T23:46:18.000Z"
        },
        {
            "id": 3681581,
            "content_html": "",
            "url": "https://finance.sina.cn/7x24/2024-07-04/detail-incaxnru7660928.d.html",
            "title": "【河南：支持郑州构建郑庆哈城市算力网大通道】《2024年河南省大数据产业发展工作方案》近日印发，其中提到，强化算力资源供应。深度融入全国一体化算力体系建设，支持郑州市构建郑庆哈城市算力网大通道。提高国家超级计算郑州中心、中原人工智能计算中心算力使用率，积极推动国家超算互联网核心节点、郑州人工智能计算中心、郑州城市算力网等重点项目建设，力争全省算力规模突破5EFLOPS。支持郑州市建设算网智能调度系统，提升城市算力供给水平和协调调度能力。面向智能制造、无人驾驶等实时性强、计算量高的场景，探索构建城市内边缘算力供给体系，在网络边缘侧、用户设备侧建设一批边缘数据中心及计算中心。",
            "date_modified": "2024-07-03T23:44:41.000Z"
        },
        {
            "id": 3681580,
            "content_html": "",
            "url": "https://finance.sina.cn/7x24/2024-07-04/detail-incaxnrp6048917.d.html",
            "title": "【美国高温持续 山火蔓延加州北部】受超过40℃的高温天气影响，美国加利福尼亚州北部山火不断蔓延。据加州森林和消防部门发布的消息，受山火影响，已有超过2.8万名当地居民被迫撤离。截至当地时间3日中午，加州全境共有近三千处起火点，过火总面积超过565平方公里，目前该州已经发布山火红色预警。（央视）",
            "date_modified": "2024-07-03T23:43:54.000Z"
        },
        {
            "id": 3681578,
            "content_html": "",
            "url": "https://finance.sina.cn/7x24/2024-07-04/detail-incaxnrr8778339.d.html",
            "title": "【北京“626”楼市新政落地首周：新房和二手房网签量大涨，市场活跃度大升】 “新政出来后一直在带客户看房。”一位主攻新房销售的中介机构经纪人告诉记者，周末实在跑不过来，有几个客户只好委托给团队中的其他同事协助带看。根据北京住建委公布的数据统计，6月27日至7月2日，北京新房住宅网签量为1450套，存量房（二手房）网签量为4068套，较新政出台前（6月20日至6月25日）950套和3020套有较大程度提升，分别增长52.6%和34.7%。（证券日报）",
            "date_modified": "2024-07-03T23:43:23.000Z"
        },
        {
            "id": 3681576,
            "content_html": "",
            "url": "https://finance.sina.cn/7x24/2024-07-04/detail-incaxnrr8778001.d.html",
            "title": "【哥伦比亚总统任命新任内政部长和武装力量总司令】当地时间7月3日，哥伦比亚总统佩特罗宣布，胡安·费尔南多·克里斯托将接替贝拉斯科出任内政部长，同时任命海军上将弗朗西斯科·埃尔南多·库比德斯·格拉纳多斯出任哥伦比亚武装力量总司令。本周早些时候，佩特罗已更换司法部长、农业部长和交通部长等多位内阁成员。",
            "date_modified": "2024-07-03T23:41:57.000Z"
        },
        {
            "id": 3681573,
            "content_html": "",
            "url": "https://finance.sina.cn/7x24/2024-07-04/detail-incaxnru7659160.d.html",
            "title": "【46家上市公司已发布半年度业绩预告：其中41家预喜，占比近九成】 随着2024年上半年收官，上市公司半年度业绩预告相继出炉。截至7月3日收盘，共46家A股公司披露2024年半年度业绩预告，41家公司业绩预喜（包括预增、续盈、扭亏），占比近九成，其中20家公司业绩预增。从预告净利润上限来看，27家公司预计上半年净利润超1亿元。其中，立讯精密、三花智控、捷佳伟创、永泰能源、巨星科技净利润规模预计突破10亿元。“从上市公司目前预披露数据来看，上半年业绩总体较为乐观。同时，上市公司作为管窥经济发展的窗口，也预示着我国经济的向好态势。”实用金融商学执行院长罗攀表示，智能制造、生物医药等科技创新企业表现出较强韧性。（证券日报）",
            "date_modified": "2024-07-03T23:39:51.000Z"
        },
        {
            "id": 3681569,
            "content_html": "",
            "title": "【北交所8天受理28家企业上市申请】 据记者统计，上半年，北交所共计受理30家企业的上市申请；6月，北交所出现“受理潮”。6月21日至28日短短8天，北交所共计受理了28家企业的上市申请，其中6月26日、27日、28日，北交所受理企业数量分别为6家、6家、7家。这显示，北交所仍是拟上市企业的主流选择之一。上述28家企业上年度平均营收、净利润分别约为5.78亿元、6500万元，其中半数为国家级专精特新“小巨人”企业。业内人士认为，与沪深交易所错位协同发展，今年以来北交所继续高质量扩容，“打造服务创新型中小企业主阵地”特点突出，市场功能初步发挥。（上海证券报）",
            "date_modified": "2024-07-03T23:35:25.000Z"
        },
        {
            "id": 3681564,
            "content_html": "",
            "title": "【北京观复未提前告知便裁员80人？多名被裁员工已申请仲裁】近日，有博主在某社交平台发文称，2024年5月31日，其所在公司“北京观复文化有限公司” （以下简称“北京观复”）在事先未与员工或员工代表进行任何沟通的情况下，单方面发布解除劳动关系通知，人数达到80余人，裁员理由为“因劳动合同订立时所依据的客观情况发生重大变化”。7月2日，北京观复多名员工向记者证实了此事。他们表示，因企业至今未提供合理赔偿方案，目前10余名员工已申请劳动仲裁。同日，记者致电北京观复相关负责人了解情况，电话在接通后被挂断。相关资料显示，北京观复成立于2016年，是一家以从事文化艺术业为主的企业。马未都于2016年6月任法人代表，持股超95%，但公司在2024年6月24日进行了法人变更。（央广网）",
            "date_modified": "2024-07-03T23:30:16.000Z"
        }
    ]
}