{
    "version": "https://jsonfeed.org/version/1",
    "title": "新浪新闻",
    "home_page_url": "https://tk14.github.io/sina-news/",
    "feed_url": "https://tk14.github.io/sina-news/rss.json",
    "description": "新浪全球实时财经新闻直播",
    "items": [
        {
            "id": 2291081,
            "content_html": "",
            "url": "https://finance.sina.cn/7x24/2021-08-25/detail-ikqcfncc4796297.d.html",
            "title": "欧洲地中海地震中心：危地马拉近岸发生5.2级地震。",
            "date_modified": "2021-08-24T16:29:04.000Z"
        },
        {
            "id": 2291078,
            "content_html": "",
            "url": "https://finance.sina.cn/7x24/2021-08-25/detail-ikqciyzm3398937.d.html",
            "title": "德国总理默克尔：七国集团会议并没有导致8月31日从喀布尔撤离的最后期限的延长。",
            "date_modified": "2021-08-24T16:23:18.000Z"
        },
        {
            "id": 2291077,
            "content_html": "",
            "url": "https://finance.sina.cn/7x24/2021-08-25/detail-ikqcfncc4795641.d.html",
            "title": "  丰田汽车2021财年下半年将把销往供应商的钢制材料价格提高大约2万日元/吨。",
            "date_modified": "2021-08-24T16:22:43.000Z"
        },
        {
            "id": 2291076,
            "content_html": "",
            "url": "https://finance.sina.cn/7x24/2021-08-25/detail-ikqcfncc4795297.d.html",
            "title": "北京时间2021年8月24日23时41分，我国在西昌卫星发射中心用长征三号乙运载火箭，成功将通信技术试验卫星七号发射升空。卫星顺利进入预定轨道，发射任务获得圆满成功。此次任务是长征系列运载火箭的第386次飞行。（央视）",
            "date_modified": "2021-08-24T16:19:48.000Z"
        },
        {
            "id": 2291075,
            "content_html": "",
            "url": "https://finance.sina.cn/7x24/2021-08-25/detail-ikqcfncc4795252.d.html",
            "title": "阿富汗塔利班发言人穆贾希德：我们想与中国和所有国家都保持良好关系，会寻求与中国发展经济和友好关系。（央视）",
            "date_modified": "2021-08-24T16:19:11.000Z"
        },
        {
            "id": 2291074,
            "content_html": "",
            "url": "https://finance.sina.cn/7x24/2021-08-25/detail-ikqciyzm3398400.d.html",
            "title": "谷歌母公司Alphabet旗下自动驾驶部门Waymo：自动驾驶出租车在美国旧金山开始提供乘车服务。 自动驾驶出租车将配备安全司机驾驶。 精选用户组可以通过它的应用叫车。",
            "date_modified": "2021-08-24T16:18:35.000Z"
        },
        {
            "id": 2291073,
            "content_html": "",
            "url": "https://finance.sina.cn/7x24/2021-08-25/detail-ikqcfncc4795188.d.html",
            "title": "【美国坚持8月31日阿富汗撤军期限 拒绝G-7提出的延长要求】① 据一位高级政府官员透露，美国总统拜登决定坚持他设定的从喀布尔机场撤离的最后期限，给上万人留下不到一周时间飞离塔利班控制的阿富汗。 这个决定意味着拜登在周二的七国集团峰会上拒绝了美国最亲密盟国提出的延长8月31日最后期限的要求；② 一位知情人士说，鉴于ISIS-K或其他伊斯兰武装组织可能发动恐怖袭击，令美军面临安全风险，五角大楼建议拜登坚持这个最后期限。 拜登暂时同意了五角大楼的观点，但要求制定应急计划，并重申了他的承诺，会撤离所有现在想离开的美国人。撤离时间表将部分取决于塔利班在未来几天的合作；③ 由英国首相鲍里斯·约翰逊召集的此次虚拟峰会可能是说服拜登推迟完成撤军日期的最后一次机会。这实际上意味着，喀布尔机场的平民撤离必须在未来几天内结束，以便有足够的时间撤走剩余的美国和其他国家部队。 在七国集团会谈开始之际，塔利班重申不接受延期到8月31日之后。",
            "date_modified": "2021-08-24T16:18:18.000Z"
        },
        {
            "id": 2291071,
            "content_html": "",
            "url": "https://finance.sina.cn/7x24/2021-08-25/detail-ikqciyzm3397289.d.html",
            "title": "欧盟委员会主席冯德莱恩：G7集团认为喀布尔机场应该停运至撤离结束。",
            "date_modified": "2021-08-24T16:05:48.000Z"
        },
        {
            "id": 2291070,
            "content_html": "",
            "url": "https://finance.sina.cn/7x24/2021-08-25/detail-ikqcfncc4794052.d.html",
            "title": "中概股持续走高，贝壳(BEKE.N)现涨超15%，达达集团(DADA.O)涨近14%，BOSS直聘(BZ.O)涨约12%，富途控股(FUTU.O)涨超11%。",
            "date_modified": "2021-08-24T16:05:37.000Z"
        },
        {
            "id": 2291069,
            "content_html": "",
            "url": "https://finance.sina.cn/7x24/2021-08-25/detail-ikqcfncc4793750.d.html",
            "title": "英国首相约翰逊：我们已经从喀布尔撤离了9000人。",
            "date_modified": "2021-08-24T16:02:34.000Z"
        },
        {
            "id": 2291067,
            "content_html": "",
            "title": "美国政府高级官员：在撤离人员获准进入美国之前，美国情报、执法和反恐官员将进行“强有力的安全问题处理”。",
            "date_modified": "2021-08-24T15:59:31.000Z"
        },
        {
            "id": 2291065,
            "content_html": "",
            "url": "https://finance.sina.cn/7x24/2021-08-24/detail-ikqcfncc4793303.d.html",
            "title": "九毛九(09922.HK)：2021年上半年新开58间餐厅，包括1间九毛九餐厅、55间太二餐厅、1间怂重庆火锅厂餐厅及1间2颗鸡蛋煎饼加盟餐厅。我们亦于同期关闭13间自营餐厅。",
            "date_modified": "2021-08-24T15:56:15.000Z"
        },
        {
            "id": 2291064,
            "content_html": "",
            "url": "https://finance.sina.cn/7x24/2021-08-24/detail-ikqcfncc4793112.d.html",
            "title": "【因需求强劲 波罗的海干散货运价指数升至逾11年高位】波罗的海干散货运价指数周二升至逾11年高位，受助于强劲需求。海岬型船运价指数延续连续12个交易日上升。波罗的海整体干散货运价指数上涨54点至4201点，为2010年中以来高位。海岬型船运价指数跳升92点或1.5%，至6206点，接近12年高位。海岬型船日均获利大涨764美元至51472美元。巴拿马型船运价指数上涨37点或1%，至六周高位3846点。巴拿马型船日均获利增加333美元至34615元。超灵便型船运价指数触及历史新高（2017年以来记录数据），上涨40点，报3343点。",
            "date_modified": "2021-08-24T15:53:02.000Z"
        },
        {
            "id": 2291063,
            "content_html": "",
            "url": "https://finance.sina.cn/7x24/2021-08-24/detail-ikqciyzm3396332.d.html",
            "title": "  【媒体：福岛第一核电站核污染水将通过海底隧道排放入海】日本媒体当地时间24日援引日本政府相关人士的话报道称，关于福岛第一核电站核污染水排放入海问题，日本政府和东京电力公司已基本敲定，将修建一条从福岛第一核电站通往近海的海底隧道，核污染水经海水稀释后，通过该隧道引流到距离海岸1公里的海中。今年4月，日本政府正式决定将福岛第一核电站核污染水排入大海，此举引发多方不满。（央视）",
            "date_modified": "2021-08-24T15:52:24.000Z"
        },
        {
            "id": 2291061,
            "content_html": "",
            "url": "https://finance.sina.cn/7x24/2021-08-24/detail-ikqciyzm3396255.d.html",
            "title": "九毛九(09922.HK)2021年上半年营收（亿元）：前值9.77，预期20.33，公布20.21。",
            "date_modified": "2021-08-24T15:50:46.000Z"
        },
        {
            "id": 2291060,
            "content_html": "",
            "url": "https://finance.sina.cn/7x24/2021-08-24/detail-ikqcfncc4792962.d.html",
            "title": "九毛九(09922.HK)2021年上半年净利润（亿元）：前值-0.86，公布1.86。",
            "date_modified": "2021-08-24T15:50:15.000Z"
        },
        {
            "id": 2291055,
            "content_html": "",
            "url": "https://finance.sina.cn/7x24/2021-08-24/detail-ikqcfncc4792057.d.html",
            "title": "DraftKings(DKNG.O)上涨4.8%，此前与美国体育博彩技术开发商Simplebet达成协议扩大游戏内服务。",
            "date_modified": "2021-08-24T15:38:03.000Z"
        },
        {
            "id": 2291053,
            "content_html": "",
            "url": "https://finance.sina.cn/7x24/2021-08-24/detail-ikqcfncc4791977.d.html",
            "title": "Peloton(PTON.O)涨超5%，此前公司在美国推出了新的带有安全功能的跑步机。",
            "date_modified": "2021-08-24T15:36:35.000Z"
        },
        {
            "id": 2291049,
            "content_html": "",
            "url": "https://finance.sina.cn/7x24/2021-08-24/detail-ikqcfncc4791777.d.html",
            "title": "【日本2021年上半年出生人口40.5万，创2000年以来新低】日本厚生劳动省当地时间24日公布的人口动态统计数据显示，2021年上半年，日本出生人口为40.5029万，同比减少2.568万。上半年初步统计结果创2000年以来新低。据悉，2020年日本全年出生人口为84.0832万，创历史新低。数据显示，2021年日本全年出生人口数量很有可能跌破80万。据统计，2021年上半年日本出生人口同比减少6%。其中，今年1月至2月出生人口为12.3531万，同比减少12.6%，大大拉低了上半年数据。6月出生人口为7.1031万，同比减少2.7%。初步统计数据中包括居住在日本的外国人以及居住在国外的日本人。（央视）",
            "date_modified": "2021-08-24T15:32:40.000Z"
        },
        {
            "id": 2291047,
            "content_html": "",
            "url": "https://finance.sina.cn/7x24/2021-08-24/detail-ikqciyzm3394942.d.html",
            "title": "【王毅同荷兰外交大臣通电话】24日，国务委员兼外长王毅应约同荷兰外交大臣卡格通电话。双方重点就阿富汗局势交换了意见。王毅说，美国是阿富汗问题的始作俑者，更不应一走了之，也不应又想着实施什么制裁。当务之急是负起责任，处理好喀布尔机场出现的乱局，同时也应向阿富汗提供必要的紧急援助，采取实际行动帮助阿富汗局势实现平稳过渡。（央视）",
            "date_modified": "2021-08-24T15:32:06.000Z"
        },
        {
            "id": 2291046,
            "content_html": "",
            "url": "https://finance.sina.cn/7x24/2021-08-24/detail-ikqciyzm3394667.d.html",
            "title": "市场消息：Shopify(SHOP.N)总裁HARLEY FINKELSTEIN表示公司不会向TikTok提供客户数据访问权。",
            "date_modified": "2021-08-24T15:28:24.000Z"
        },
        {
            "id": 2291045,
            "content_html": "",
            "url": "https://finance.sina.cn/7x24/2021-08-24/detail-ikqcfncc4791422.d.html",
            "title": "美国政府官员：美国方面告诉塔利班，美国在8月31日之前是否完成撤军取决于与塔利班协助撤离的合作。",
            "date_modified": "2021-08-24T15:27:49.000Z"
        },
        {
            "id": 2291044,
            "content_html": "",
            "url": "https://finance.sina.cn/7x24/2021-08-24/detail-ikqcfncc4791378.d.html",
            "title": "美国政府官员：拜登已要求五角大楼制订应急计划，如有必要，可以在阿富汗多呆一段时间。",
            "date_modified": "2021-08-24T15:27:02.000Z"
        },
        {
            "id": 2291043,
            "content_html": "",
            "url": "https://finance.sina.cn/7x24/2021-08-24/detail-ikqciyzm3394454.d.html",
            "title": "美国白宫官员：G7集团会议已经结束。",
            "date_modified": "2021-08-24T15:25:40.000Z"
        },
        {
            "id": 2291041,
            "content_html": "",
            "url": "https://finance.sina.cn/7x24/2021-08-24/detail-ikqciyzm3394419.d.html",
            "title": "世界粮食计划署执行主任：非常担心无法筹集到援助阿富汗所需的2亿美元资金，那么400万人的生命将处于危险之中。",
            "date_modified": "2021-08-24T15:25:09.000Z"
        },
        {
            "id": 2291040,
            "content_html": "",
            "url": "https://finance.sina.cn/7x24/2021-08-24/detail-ikqciyzm3394407.d.html",
            "title": "世界粮食计划署执行主任：阿富汗人民现在需要援助，政治问题需要尽快解决。",
            "date_modified": "2021-08-24T15:25:00.000Z"
        },
        {
            "id": 2291038,
            "content_html": "",
            "title": "世界粮食计划署执行主任：如果阿富汗经济停止运转或进一步恶化，将是一番“人间地狱”的景象。",
            "date_modified": "2021-08-24T15:22:34.000Z"
        },
        {
            "id": 2291034,
            "content_html": "",
            "url": "https://finance.sina.cn/7x24/2021-08-24/detail-ikqciyzm3393836.d.html",
            "title": "市场消息：马士基拟投资14亿美元，用于打造一只甲醇为动力的、更加绿色的船队，预计将从2024年开始交货。",
            "date_modified": "2021-08-24T15:17:55.000Z"
        },
        {
            "id": 2291028,
            "content_html": "",
            "url": "https://finance.sina.cn/7x24/2021-08-24/detail-ikqcfncc4789802.d.html",
            "title": "据日经新闻：东京电力公司将从离岸1公里处开始排放福岛核电站废水。",
            "date_modified": "2021-08-24T15:08:39.000Z"
        },
        {
            "id": 2291027,
            "content_html": "",
            "title": "  中国地震台网正式测定：08月24日22时47分在马里亚纳群岛（北纬12.60度，东经145.20度）发生5.2级地震，震源深度50千米。",
            "date_modified": "2021-08-24T15:08:30.000Z"
        },
        {
            "id": 2291025,
            "content_html": "",
            "url": "https://finance.sina.cn/7x24/2021-08-24/detail-ikqcfncc4789479.d.html",
            "title": "俄罗斯总统普京：俄方在密切关注阿富汗局势，但不会干预，更不会卷入一场各方混战的军事冲突。",
            "date_modified": "2021-08-24T15:05:18.000Z"
        },
        {
            "id": 2291021,
            "content_html": "",
            "url": "https://finance.sina.cn/7x24/2021-08-24/detail-ikqciyzm3392310.d.html",
            "title": "美国总统拜登：不可能把所有人都撤出阿富汗。",
            "date_modified": "2021-08-24T15:01:31.000Z"
        },
        {
            "id": 2291020,
            "content_html": "",
            "url": "https://finance.sina.cn/7x24/2021-08-24/detail-ikqcfncc4788908.d.html",
            "title": "英国首相约翰逊：对塔利班政权的承认和资金援助是对付塔利班的筹码。",
            "date_modified": "2021-08-24T14:59:40.000Z"
        },
        {
            "id": 2291019,
            "content_html": "",
            "url": "https://finance.sina.cn/7x24/2021-08-24/detail-ikqciyzm3392056.d.html",
            "title": "俄罗斯总统普京：俄罗斯不打算在军事上介入阿富汗事务。",
            "date_modified": "2021-08-24T14:59:29.000Z"
        },
        {
            "id": 2291017,
            "content_html": "",
            "url": "https://finance.sina.cn/7x24/2021-08-24/detail-ikqcfncc4788830.d.html",
            "title": "在库克掌舵苹果公司的十年间，该公司围绕其旗舰产品iPhone不断扩展设备和服务的生态系统，使得其营收和利润增长了两倍多，市值也从乔布斯辞职那天的约3500亿美元增长到如今的近2.5万亿美元。",
            "date_modified": "2021-08-24T14:58:26.000Z"
        },
        {
            "id": 2291016,
            "content_html": "",
            "url": "https://finance.sina.cn/7x24/2021-08-24/detail-ikqciyzm3391949.d.html",
            "title": "  昆仑能源(00135.HK)：上半年营收为647.39亿元，去年同期为467.14亿元。",
            "date_modified": "2021-08-24T14:58:02.000Z"
        },
        {
            "id": 2291015,
            "content_html": "",
            "url": "https://finance.sina.cn/7x24/2021-08-24/detail-ikqcfncc4788737.d.html",
            "title": "  昆仑能源(00135.HK)：上半年未计利息、税项、折旧及摊销前的利润为73.2亿元。",
            "date_modified": "2021-08-24T14:57:09.000Z"
        },
        {
            "id": 2291014,
            "content_html": "",
            "url": "https://finance.sina.cn/7x24/2021-08-24/detail-ikqciyzm3391890.d.html",
            "title": "  据美国证券交易委员会文件：空白支票公司KAIROUS ACQUISITION CORP提交IPO申请，拟筹资达5000万美元。",
            "date_modified": "2021-08-24T14:57:05.000Z"
        },
        {
            "id": 2291013,
            "content_html": "",
            "url": "https://finance.sina.cn/7x24/2021-08-24/detail-ikqciyzm3391833.d.html",
            "title": "  小鹏汽车（XPEV）一度涨超2.4%，该公司称，已经向挪威发货首批P7货物，意味着该公司正在进一步开拓市场。",
            "date_modified": "2021-08-24T14:56:12.000Z"
        },
        {
            "id": 2291011,
            "content_html": "",
            "url": "https://finance.sina.cn/7x24/2021-08-24/detail-ikqciyzm3391510.d.html",
            "title": "法国外交部：自撤离行动开始以来，已有近100名法国人和1500多名阿富汗人抵达法国。",
            "date_modified": "2021-08-24T14:52:38.000Z"
        },
        {
            "id": 2291010,
            "content_html": "",
            "url": "https://finance.sina.cn/7x24/2021-08-24/detail-ikqcfncc4788132.d.html",
            "title": "  【泛海控股同意向通海国际金融转让代价股份 以清偿框架服务协议贷款】中泛控股在港交所公告称，董事会宣布，于2021年8月24日（交易时段后），本公司与泛海控股及中国通海国际金融订立债务清偿协议，据此，泛海控股有条件同意（其中包括）向中国通海国际金融（或其代名人）转让代价股份，以清偿框架服务协议贷款。",
            "date_modified": "2021-08-24T14:50:20.000Z"
        },
        {
            "id": 2291009,
            "content_html": "",
            "url": "https://finance.sina.cn/7x24/2021-08-24/detail-ikqciyzm3391213.d.html",
            "title": "十年前的今天，库克正式从乔布斯手中接任苹果公司CEO。如果2011年8月24日在苹果股票上投资1000美元，截至本周一其价值将超过16866美元；如果将所有股息再投资，年回报率将超过32%，同期标普500指数的年回报率仅略高于16%。",
            "date_modified": "2021-08-24T14:50:05.000Z"
        },
        {
            "id": 2291008,
            "content_html": "",
            "url": "https://finance.sina.cn/7x24/2021-08-24/detail-ikqcfncc4788037.d.html",
            "title": "据卫星新闻：联合国人权理事会投票决定在阿富汗建立人权监督机制。",
            "date_modified": "2021-08-24T14:49:46.000Z"
        },
        {
            "id": 2291007,
            "content_html": "",
            "url": "https://finance.sina.cn/7x24/2021-08-24/detail-ikqciyzm3391129.d.html",
            "title": "【硅料价格大幅上涨，满产满销！】作为光伏产业的上游原材料，今年以来，硅料价格从每吨8万元左右的价格，涨到了每吨20万元以上，涨幅高达150%。走进目前全球最大的硅料生产企业，记者看到，所有生产线正在全速生产。负责人告诉记者，目前他们的年产能是8万吨。今年上半年，他们企业的产能利用率达到126.50%，实现产量5.06万吨。尽管生产线一直在超负荷生产，在产品库房，记者却发现，大部分的库位都是空的。工作人员告诉记者，仅有的400多吨硅料库存，也要马上发走。企业负责人告诉记者，“现在企业没有库存，真正做到满产满销。”（央视财经）",
            "date_modified": "2021-08-24T14:49:10.000Z"
        },
        {
            "id": 2291006,
            "content_html": "",
            "url": "https://finance.sina.cn/7x24/2021-08-24/detail-ikqcfncc4787888.d.html",
            "title": "美国国防部发言人Kirby：需要几天时间将所有部队撤出喀布尔。",
            "date_modified": "2021-08-24T14:48:04.000Z"
        },
        {
            "id": 2291005,
            "content_html": "",
            "title": "  美股NFT概念股强势走高，大公文化(TKAT)涨近60%，东方文化(OCG.O)涨20%，腾讯音乐(TME.N)涨11.56%，Dolphin Entertainment(DLPN.O)涨10.45%，阿里巴巴(BABA.N)涨7.4%，Hall of Fame(HOFV.O)涨5.38%，Roblox(RBLX.N)涨3.8%。",
            "date_modified": "2021-08-24T14:47:19.000Z"
        },
        {
            "id": 2291004,
            "content_html": "",
            "url": "https://finance.sina.cn/7x24/2021-08-24/detail-ikqciyzm3390946.d.html",
            "title": "  【最高法：2020年全国法院接收网上立案1080万件】最高人民法院信息中心主任许建峰24日在发布会上介绍，2020年，全国法院接收网上立案1080万件，占一审立案量的54%；1/5以上立案申请在非工作时段提交；约1/10立案申请在非工作日提交。",
            "date_modified": "2021-08-24T14:47:08.000Z"
        },
        {
            "id": 2291003,
            "content_html": "",
            "url": "https://finance.sina.cn/7x24/2021-08-24/detail-ikqcfncc4787738.d.html",
            "title": "  ICE美元指数下跌0.2%，刷新8月17日以来低点至92.80。",
            "date_modified": "2021-08-24T14:46:02.000Z"
        },
        {
            "id": 2291001,
            "content_html": "",
            "url": "https://finance.sina.cn/7x24/2021-08-24/detail-ikqcfncc4787564.d.html",
            "title": "美国国防部发言人Kirby：五角大楼可能会在美国为撤离人员寻找更多收留地。",
            "date_modified": "2021-08-24T14:43:51.000Z"
        },
        {
            "id": 2290998,
            "content_html": "",
            "url": "https://finance.sina.cn/7x24/2021-08-24/detail-ikqcfncc4787352.d.html",
            "title": "  【顺风清洁能源(01165.HK)拟5.376亿元出售多个光伏电站 25日复牌】顺风清洁能源(01165.HK)公布，于2021年8月13日，卖方(即江西顺风、上海顺能及深圳尚德)与买方(中电投新疆能源化工集团阿克苏有限公司)订立七份买卖协议，卖方将向买方出售保山长山、浚鑫、克州百事德、麦盖提、乌什、英吉沙及中建材各自100%股权，总代价为人民币5.376亿元。公司已向联交所申请股份自2021年8月25日上午九时正起于联交所恢复买卖。",
            "date_modified": "2021-08-24T14:41:27.000Z"
        },
        {
            "id": 2290997,
            "content_html": "",
            "url": "https://finance.sina.cn/7x24/2021-08-24/detail-ikqciyzm3390450.d.html",
            "title": "  【攀钢钒钛：对公司钒、钛产品中长期市场持乐观态度】攀钢钒钛在机构调研时表示，随着国内国际经济发展趋势向好，我们对公司钒、钛产品中长期市场持乐观态度。公司向大股东采购钛精矿为市场定价，采购粗钒渣为成本加合理利润模式定价。",
            "date_modified": "2021-08-24T14:41:13.000Z"
        },
        {
            "id": 2290996,
            "content_html": "",
            "url": "https://finance.sina.cn/7x24/2021-08-24/detail-ikqcfncc4787138.d.html",
            "title": "巴西雷亚尔兑美元在现货市场交易中涨2%。",
            "date_modified": "2021-08-24T14:40:00.000Z"
        },
        {
            "id": 2290994,
            "content_html": "",
            "url": "https://finance.sina.cn/7x24/2021-08-24/detail-ikqcfncc4786867.d.html",
            "title": "美国五角大楼：从喀布尔机场起飞的航班大约每45分钟一班。",
            "date_modified": "2021-08-24T14:36:32.000Z"
        },
        {
            "id": 2290993,
            "content_html": "",
            "url": "https://finance.sina.cn/7x24/2021-08-24/detail-ikqciyzm3389954.d.html",
            "title": "市场消息：在过去的24小时内，美国及其盟国从阿富汗撤离了21600人。",
            "date_modified": "2021-08-24T14:36:03.000Z"
        },
        {
            "id": 2290992,
            "content_html": "",
            "url": "https://finance.sina.cn/7x24/2021-08-24/detail-ikqcfncc4786810.d.html",
            "title": "美国7月新屋销售环比增长1%，至70.8万套，同比降幅达到27.2%，为2020年4月以来的最低水平。新房价格中值创下历史新高，达到390500美元，同比增幅18.4%。",
            "date_modified": "2021-08-24T14:35:45.000Z"
        },
        {
            "id": 2290989,
            "content_html": "",
            "url": "https://finance.sina.cn/7x24/2021-08-24/detail-ikqciyzm3389759.d.html",
            "title": "  大公文化(TKAT)盘中拉升，涨幅达60%。",
            "date_modified": "2021-08-24T14:33:13.000Z"
        },
        {
            "id": 2290986,
            "content_html": "",
            "url": "https://finance.sina.cn/7x24/2021-08-24/detail-ikqciyzm3389327.d.html",
            "title": "  【天津港集团今年货物吞吐量已突破3亿吨】今日上午11点，随着“阿克尔”轮3.3万吨矿石装卸作业完成，2021年天津港集团货物吞吐量已突破3亿吨；集装箱吞吐量完成1348万标准箱，同比增长15.8%，双创历史同期最好水平。",
            "date_modified": "2021-08-24T14:29:17.000Z"
        },
        {
            "id": 2290985,
            "content_html": "",
            "url": "https://finance.sina.cn/7x24/2021-08-24/detail-ikqciyzm3389151.d.html",
            "title": "美国白宫：拜登与七国集团其他领导人的会晤已经开始。",
            "date_modified": "2021-08-24T14:27:05.000Z"
        }
    ]
}