{
    "version": "https://jsonfeed.org/version/1",
    "title": "新浪新闻",
    "home_page_url": "https://tk14.github.io/sina-news/",
    "feed_url": "https://tk14.github.io/sina-news/rss.json",
    "description": "新浪全球实时财经新闻直播",
    "items": [
        {
            "id": 2209726,
            "content_html": "",
            "url": "https://finance.sina.cn/7x24/2021-06-16/detail-ikqcfnca1336792.d.html",
            "title": "汽车整车板块午后持续走弱，北汽蓝谷、长城汽车跌停，东风汽车、长安汽车、比亚迪跟跌。",
            "date_modified": "2021-06-16T05:25:37.000Z"
        },
        {
            "id": 2209725,
            "content_html": "",
            "url": "https://finance.sina.cn/7x24/2021-06-16/detail-ikqcfnca1336748.d.html",
            "title": "有色金属股全线下跌，华友钴业逼近跌停，赣锋锂业跌超7%，西藏矿业、宝钛股份跌超6%，寒锐钴业、锡业股份、中矿资源跌超5%。",
            "date_modified": "2021-06-16T05:25:17.000Z"
        },
        {
            "id": 2209723,
            "content_html": "",
            "title": "[芯片短缺影响 戴姆勒与大众将缩短部分工厂工作时间】受芯片短缺影响，戴姆勒和大众将削减部分工厂的工作时间。戴姆勒一位发言人表示，该公司本周将削减位于不来梅和拉施塔特的德国工厂的工作时间。大众一名发言人表示，下周，该公司将削减其沃尔夫斯堡工厂的工作时长。据悉，这不是戴姆勒第一次削减员工的工作时间。此前，在今年4月份，该公司曾表示，由于芯片短缺冲击了全球汽车生产，它将削减多达1.85万名员工的工作时间，并将暂停德国两家工厂的生产。",
            "date_modified": "2021-06-16T05:24:29.000Z"
        },
        {
            "id": 2209721,
            "content_html": "",
            "url": "https://finance.sina.cn/7x24/2021-06-16/detail-ikqciyzi9934385.d.html",
            "title": "  昇辉科技直线拉升涨超4%，子公司参与越秀服务香港IPO。",
            "date_modified": "2021-06-16T05:22:29.000Z"
        },
        {
            "id": 2209720,
            "content_html": "",
            "url": "https://finance.sina.cn/7x24/2021-06-16/detail-ikqciyzi9934275.d.html",
            "title": "【三星电子与加州大学成功演示6G太赫兹无线通信】三星电子公司表示，已与加州大学圣巴巴拉分校联合成功演示6G太赫兹无线通信技术，在6G网络研究方面取得了进展。",
            "date_modified": "2021-06-16T05:21:47.000Z"
        },
        {
            "id": 2209718,
            "content_html": "",
            "url": "https://finance.sina.cn/7x24/2021-06-16/detail-ikqciyzi9933528.d.html",
            "title": "  【英伟达收购Arm交易无法如期完成 欧洲监管部门延迟审批】由于监管部门将审查时间延迟到夏季休假之后，英伟达对ARM的收购交易将无法在明年3月份之前完成。 (路透)",
            "date_modified": "2021-06-16T05:16:58.000Z"
        },
        {
            "id": 2209717,
            "content_html": "",
            "url": "https://finance.sina.cn/7x24/2021-06-16/detail-ikqcfnca1335363.d.html",
            "title": "传智教育午后涨停，上演地天板，换手率为43.48%。",
            "date_modified": "2021-06-16T05:16:36.000Z"
        },
        {
            "id": 2209716,
            "content_html": "",
            "url": "https://finance.sina.cn/7x24/2021-06-16/detail-ikqciyzi9933165.d.html",
            "title": "鸿蒙概念午后拉升，超图软件涨超8%，润和软件、芯海科技、传智教育跟涨。",
            "date_modified": "2021-06-16T05:14:09.000Z"
        },
        {
            "id": 2209715,
            "content_html": "",
            "url": "https://finance.sina.cn/7x24/2021-06-16/detail-ikqciyzi9933143.d.html",
            "title": "【长虹牵头制定全球首个“区块链+物联网安全”国际标准】近日，由IEEE SA（国际电气与电子工程师标准协会）组织的全球标准立项会在线上召开。在本次会议中，由四川长虹电子控股集团牵头提交的《基于区块链的物联网零信任框架标准》，经过与会国际专家充分讨论，获得全票通过，正式立项，这也是全球首个“区块链+物联网安全”国际标准。",
            "date_modified": "2021-06-16T05:14:01.000Z"
        },
        {
            "id": 2209714,
            "content_html": "",
            "url": "https://finance.sina.cn/7x24/2021-06-16/detail-ikqcfnca1334788.d.html",
            "title": "【深圳将建中国（深圳）证券仲裁中心】 6月15日，深圳市委全面深化改革委员会召开会议，审议并原则通过《深圳市国际航行船舶保税燃料油经营管理试行办法》《深圳市深化国际船舶登记制度改革实施方案》《深圳国际仲裁院与深圳证券交易所共建中国（深圳）证券仲裁中心改革方案》《关于先行示范打造儿童友好型城市的意见（2021-2025年）》《关于建立健全深圳市妇女儿童人身权益保障工作机制的意见》等文件。",
            "date_modified": "2021-06-16T05:12:49.000Z"
        },
        {
            "id": 2209713,
            "content_html": "",
            "url": "https://finance.sina.cn/7x24/2021-06-16/detail-ikqciyzi9932867.d.html",
            "title": "  据英雄联盟赛事微博，2021英雄联盟全球总决赛将在上海、青岛、武汉、成都和深圳五座城市举办。",
            "date_modified": "2021-06-16T05:12:20.000Z"
        },
        {
            "id": 2209712,
            "content_html": "",
            "url": "https://finance.sina.cn/7x24/2021-06-16/detail-ikqciyzi9932709.d.html",
            "title": "  据中国畜牧业信息网统计，截至上周，全国22个省市生猪平均价为15.54元/千克，5月初以来已累计下跌32%。",
            "date_modified": "2021-06-16T05:11:16.000Z"
        },
        {
            "id": 2209711,
            "content_html": "",
            "url": "https://finance.sina.cn/7x24/2021-06-16/detail-ikqciyzi9932372.d.html",
            "title": "港股有色金属板块午后继续下挫，中国宏桥跌7.8%，紫金矿业跌7.5%，中国铝业跌6%，赣锋锂业跌5.7%。",
            "date_modified": "2021-06-16T05:09:34.000Z"
        },
        {
            "id": 2209709,
            "content_html": "",
            "url": "https://finance.sina.cn/7x24/2021-06-16/detail-ikqcfnca1334025.d.html",
            "title": "汽车整车板块午后持续下挫，长城汽车、东风汽车跌超9%，海马汽车此前跌停，北汽蓝谷、长安汽车、比亚迪、江淮汽车跟跌。",
            "date_modified": "2021-06-16T05:08:08.000Z"
        },
        {
            "id": 2209708,
            "content_html": "",
            "url": "https://finance.sina.cn/7x24/2021-06-16/detail-ikqciyzi9931927.d.html",
            "title": "特斯拉CEO马斯克：大多数人都不知道特斯拉的空气净化系统有多好，我们的系统比其他任何车都好10倍。",
            "date_modified": "2021-06-16T05:06:46.000Z"
        },
        {
            "id": 2209706,
            "content_html": "",
            "title": "  中国地震台网正式测定：06月16日12时43分在印尼塞兰岛海域（南纬3.50度，东经129.45度）发生5.9级地震，震源深度10千米。",
            "date_modified": "2021-06-16T05:03:33.000Z"
        },
        {
            "id": 2209704,
            "content_html": "",
            "url": "https://finance.sina.cn/7x24/2021-06-16/detail-ikqciyzi9930753.d.html",
            "title": "【国家卫健委：将天津市等17个城市确定为公立医院综合改革第二批国家级示范城市】国家卫健委发布关于确定公立医院综合改革第二批国家级示范城市的通知。决定将天津市等17个城市确定为公立医院综合改革第二批国家级示范城市，天津市北辰区不再单独作为示范地方。",
            "date_modified": "2021-06-16T04:59:29.000Z"
        },
        {
            "id": 2209703,
            "content_html": "",
            "url": "https://finance.sina.cn/7x24/2021-06-16/detail-ikqciyzi9930239.d.html",
            "title": "  【代县“6·10”透水事故救援工作在严密防爆措施保护下完成排水 已发现11名遇难者】 6月16日，代县大红才铁矿“6·10”透水事故救援工作已完成井下被困人员位置排水工作，正在3米多深的泥浆砂石中继续搜救。截至目前，已发现11名遇难者。目前，救援工作的重点是按照已确定排爆方案消除隐患，同时在泥砂中寻找最后2名被困人员。 据了解，事故调查前期工作已经启动。（山西发布）",
            "date_modified": "2021-06-16T04:55:24.000Z"
        },
        {
            "id": 2209701,
            "content_html": "",
            "title": "  中国地震台网自动测定：06月16日12时43分在印尼塞兰岛附近（南纬3.40度，东经129.57度）发生6.1级左右地震，最终结果以正式速报为准",
            "date_modified": "2021-06-16T04:50:38.000Z"
        },
        {
            "id": 2209699,
            "content_html": "",
            "url": "https://finance.sina.cn/7x24/2021-06-16/detail-ikqcfnca1330609.d.html",
            "title": "  【集邦咨询：TCON面临短缺 高端机种首当其冲】TrendForce集邦咨询表示，近期TCON（Timing Controller）的短缺对大尺寸面板出货造成不小影响，其中又以高端机种为最。主因是高端TCON主要集中于12英寸晶圆厂生产，除了面临严重的产能排挤情况之外，后段逻辑封测产能的吃紧，对于TCON的供货再添隐忧。尤其是打线封装产能，因高端TCON所需要的制程时间较一般TCON来得长，故更容易造成供货缺口逐渐扩大。在逻辑芯片封测产能扩张的速度未能及时应付各种应用产品需求激增的状况下，高端TCON的缺口短期内恐难以获得有效的缓解。",
            "date_modified": "2021-06-16T04:46:21.000Z"
        },
        {
            "id": 2209696,
            "content_html": "",
            "url": "https://finance.sina.cn/7x24/2021-06-16/detail-ikqciyzi9927710.d.html",
            "title": "据英国金融时报：富时罗素可能将208家违反ESG评估方法的公司从该指数中剔除。",
            "date_modified": "2021-06-16T04:39:42.000Z"
        },
        {
            "id": 2209694,
            "content_html": "",
            "url": "https://finance.sina.cn/7x24/2021-06-16/detail-ikqciyzi9925904.d.html",
            "title": "美国白宫：拜登将在与普京会晤后立即返回华盛顿。",
            "date_modified": "2021-06-16T04:29:06.000Z"
        },
        {
            "id": 2209691,
            "content_html": "",
            "url": "https://finance.sina.cn/7x24/2021-06-16/detail-ikqcfnca1327324.d.html",
            "title": "莎莎国际全年净亏损3.514亿港元，市场预估亏损2.508亿港元。",
            "date_modified": "2021-06-16T04:27:02.000Z"
        },
        {
            "id": 2209689,
            "content_html": "",
            "url": "https://finance.sina.cn/7x24/2021-06-16/detail-ikqcfnca1326242.d.html",
            "title": "市场消息：日本内阁府表示，高级医疗顾问尾身美次将在北京时间16点50分左右召开新闻发布会，日本经济再生大臣西村康稔将缺席发布会。",
            "date_modified": "2021-06-16T04:21:41.000Z"
        },
        {
            "id": 2209686,
            "content_html": "",
            "url": "https://finance.sina.cn/7x24/2021-06-16/detail-ikqciyzi9922631.d.html",
            "title": "  【腾讯关联公司注册资本增至202亿 增幅10000％】天眼查App显示，6月16日，深圳市腾讯斐泰科技有限公司发生工商变更，股东新增深圳市腾讯科融企业管理有限公司，同时注册资本由2亿人民币变更为202亿人民币，增幅10000％。",
            "date_modified": "2021-06-16T04:12:13.000Z"
        },
        {
            "id": 2209685,
            "content_html": "",
            "url": "https://finance.sina.cn/7x24/2021-06-16/detail-ikqcfnca1324380.d.html",
            "title": "【IDC：第一季度中国IT安全硬件市场规模同比增长18.2%】IDC《2021年第一季度中国IT安全硬件市场跟踪报告》显示，2021年第一季度中国IT安全硬件市场厂商整体收入约为4.7亿美元（约合30.5亿元人民币），厂商收入规模较去年同期实现了快速增长，涨幅为18.2%。",
            "date_modified": "2021-06-16T04:12:01.000Z"
        },
        {
            "id": 2209684,
            "content_html": "",
            "url": "https://finance.sina.cn/7x24/2021-06-16/detail-ikqciyzi9921415.d.html",
            "title": "生态环境部（国家核安全局）：台山核电厂1号机组堆芯共有60000多根燃料棒，目前推算燃料棒包壳破损数量约为5根左右，破损燃料棒占总数比例小于0.01%，远低于设计中假设的燃料组件最大破损比例（0.25%）。",
            "date_modified": "2021-06-16T04:07:04.000Z"
        },
        {
            "id": 2209680,
            "content_html": "",
            "url": "https://finance.sina.cn/7x24/2021-06-16/detail-ikqcfnca1321244.d.html",
            "title": "【字节跳动入股心潮无限科技公司 后者经营范围含企业管理】天眼查App显示，近日，北京心潮无限科技有限公司发生工商变更，新增股东字节跳动关联公司北京量子跃动科技有限公司、北京心潮澎拜信息咨询中心（有限合伙），同时公司注册资本由100万元人民币增至约115.6万元人民币，增幅约15.6%。北京心潮无限科技有限公司成立于2021年4月，法定代表人为周晶锦，经营范围包含基础软件服务；应用软件服务；计算机系统服务；企业管理；经济贸易咨询；承办展览展示活动等。",
            "date_modified": "2021-06-16T03:57:11.000Z"
        },
        {
            "id": 2209679,
            "content_html": "",
            "url": "https://finance.sina.cn/7x24/2021-06-16/detail-ikqciyzi9919360.d.html",
            "title": "【新加坡公布人口普查数据 过去十年人口增速减慢】新加坡统计局今天（16日）公布“2020年全国人口普查”第一批数据，数据显示新加坡总人口为568.58万人，过去10年增加60万人口，平均每年增长约1.1％，增长速度较上一个10年的2.5%放缓，也是上世纪70年代以来人口最慢增长的10年。（央视新闻）",
            "date_modified": "2021-06-16T03:57:05.000Z"
        },
        {
            "id": 2209678,
            "content_html": "",
            "url": "https://finance.sina.cn/7x24/2021-06-16/detail-ikqcfnca1319225.d.html",
            "title": "港股长城汽车早盘尾段跌幅扩大至10%，其他汽车股跌幅也有所扩大，比亚迪股份跌超5%，东风集团股份、恒大汽车、广汽集团跌超4%，五菱汽车、吉利汽车跌3.5%。",
            "date_modified": "2021-06-16T03:48:43.000Z"
        },
        {
            "id": 2209677,
            "content_html": "",
            "url": "https://finance.sina.cn/7x24/2021-06-16/detail-ikqcfnca1319036.d.html",
            "title": "马斯克：即将在特斯拉汽车上装配新的空调系统，将带来更加安静的体验。",
            "date_modified": "2021-06-16T03:47:59.000Z"
        },
        {
            "id": 2209675,
            "content_html": "",
            "url": "https://finance.sina.cn/7x24/2021-06-16/detail-ikqciyzi9916146.d.html",
            "title": "【安徽：支持国轩高科、蔚来、江淮等企业在节能技术领域积极攻关】6月16日，《安徽省节能环保产业发展规划(2021~2023年)》发布。根据规划，安徽省鼓励合肥国轩电池有限公司、阳光电源股份有限公司等龙头企业加速动力锂电池、太阳能光伏等新能源产业先进工艺研发和推广利用，大力延伸相关产业链。支持蔚来汽车(安徽)有限公司、安徽江淮汽车集团股份有限公司等汽车企业在关键节能技术、核心领域等方面积极攻关，打造全国节能汽车生产基地，提高核心零部件国产化，重要零部件本土化水平。",
            "date_modified": "2021-06-16T03:42:27.000Z"
        },
        {
            "id": 2209674,
            "content_html": "",
            "title": "交通运输部办公厅发布关于征求《基于区块链的进口集装箱电子放货平台建设指南（征求意见稿）》意见的函。",
            "date_modified": "2021-06-16T03:41:14.000Z"
        },
        {
            "id": 2209671,
            "content_html": "",
            "url": "https://finance.sina.cn/7x24/2021-06-16/detail-ikqciyzi9914388.d.html",
            "title": "国盛证券：给予时代天使买进的初始评级。",
            "date_modified": "2021-06-16T03:35:34.000Z"
        },
        {
            "id": 2209669,
            "content_html": "",
            "url": "https://finance.sina.cn/7x24/2021-06-16/detail-ikqciyzi9914246.d.html",
            "title": "【中国信通院：前5个月国内手机市场保持快速增长 整体呈现上升趋势】中国信通院报告指出，4、5月份手机出货量同比有所下降，主要受三方面因素影响：一是一季度国内市场手机出货量同比增长超过100%，需求提前释放；二是产业链上游手机芯片供应偏紧；三是华为出货量大幅下降，其他厂商未能完全弥补华为空缺。从2021年前五个月的数据来看，国内手机市场保持快速增长，整体呈现上升趋势，其中5G手机实现大幅度增长。",
            "date_modified": "2021-06-16T03:34:55.000Z"
        },
        {
            "id": 2209667,
            "content_html": "",
            "url": "https://finance.sina.cn/7x24/2021-06-16/detail-ikqcfnca1315753.d.html",
            "title": "上证综指连续三天走低，午盘收跌0.77%，报3529.11点。贵州茅台对指数下跌拖累最大，下跌1.7%。 太极集团跌幅最大，下跌10.0%。午盘交易中，1,579支股票中949支下跌，545支上涨；5个类股中4个类股走低，以工业股为首。",
            "date_modified": "2021-06-16T03:33:39.000Z"
        },
        {
            "id": 2209665,
            "content_html": "",
            "url": "https://finance.sina.cn/7x24/2021-06-16/detail-ikqciyzi9912942.d.html",
            "title": "  【小米、快手入股人人视频】天眼查App显示，6月15日，人人视频关联公司上海众多美网络科技有限公司发生工商变更，新增股东小米科技有限责任公司、北京快手科技有限公司等，同时公司注册资本由约226.3万人民币增至约259.8万人民币，增幅约14.8%。",
            "date_modified": "2021-06-16T03:29:48.000Z"
        },
        {
            "id": 2209664,
            "content_html": "",
            "url": "https://finance.sina.cn/7x24/2021-06-16/detail-ikqciyzi9912854.d.html",
            "title": "【网达软件：作为咪咕的主要技术合作伙伴 在技术支撑和赛事运营等方面全力保障赛事播出的顺利进行】网达软件在互动平台表示，中国移动咪咕公司作为中央广播电视总台奥运会、欧洲杯、冬奥会、世界杯赛事转播顶级合作伙伴，正在和即将进行支撑相关赛事的播出工作。网达软件作为咪咕的主要技术合作伙伴，在技术支撑和赛事运营等方面全力保障赛事播出的顺利进行。",
            "date_modified": "2021-06-16T03:29:25.000Z"
        },
        {
            "id": 2209662,
            "content_html": "",
            "url": "https://finance.sina.cn/7x24/2021-06-16/detail-ikqcfnca1314269.d.html",
            "title": "深证成指跌幅扩大至2%。",
            "date_modified": "2021-06-16T03:27:40.000Z"
        },
        {
            "id": 2209661,
            "content_html": "",
            "url": "https://finance.sina.cn/7x24/2021-06-16/detail-ikqcfnca1313735.d.html",
            "title": "【合肥葛洲坝中和府摇号选房违规操作处理公布，2人被行政拘留】刚刚，葛洲坝中和府摇号选房违规操作最新处理进展来了。记者从合肥市公安局包河分局了解到，7名违法行为人被处罚，其中2人被行政拘留。经调查，6月11日，在合肥葛洲坝中和府商品住房（6#、7#、10#楼共89套）按序选房环节中，合肥葛洲坝房地产开发有限公司裴某某、潘某某以贴虚假“已售”标签的方式，达到特定利益购房者购买指定房屋的目的，破坏了现场摇号选房的正常进行，影响其他购房者公平公正选房。（合肥日报）",
            "date_modified": "2021-06-16T03:25:12.000Z"
        },
        {
            "id": 2209658,
            "content_html": "",
            "url": "https://finance.sina.cn/7x24/2021-06-16/detail-ikqcfnca1312115.d.html",
            "title": "  【安利股份：公司占苹果公司内部份额逐步扩大与耐克的合作预计三四季度量产】安利股份在接受机构调研时表示，目前苹果公司正在积极开发聚氨酯合成革及复合材料替代塑料、合金。公司占苹果公司内部份额逐步扩大，正逐渐替代韩国、日本等供应商。包括苹果公司在内的电子产品品类，正逐步成为公司强劲的新动能和新增长点。同时，目前与耐克合作处于开发阶段，预计三四季度正式量产，未来将有较大幅度增长。在汽车内饰领域，公司已成为一汽丰田、长城汽车的供应商，与小鹏汽车等新能源汽车有一定初步合作。",
            "date_modified": "2021-06-16T03:19:31.000Z"
        },
        {
            "id": 2209656,
            "content_html": "",
            "url": "https://finance.sina.cn/7x24/2021-06-16/detail-ikqcfnca1311413.d.html",
            "title": "  【广电计量：公司可开展燃气泄露探测器校准业务 目前业务量占总体业务比例很小】广电计量在互动平台表示，公司可开展燃气泄露探测器校准业务，目前业务量占公司总体业务比例很小。",
            "date_modified": "2021-06-16T03:16:35.000Z"
        },
        {
            "id": 2209655,
            "content_html": "",
            "url": "https://finance.sina.cn/7x24/2021-06-16/detail-ikqciyzi9909577.d.html",
            "title": "  【格力电器关联公司注册格力明珠商标】天眼查App显示，近日，珠海格力电器股份有限公司申请注册“格力·明珠”商标，国际分类为灯具空调，商标状态为申请中。",
            "date_modified": "2021-06-16T03:16:25.000Z"
        },
        {
            "id": 2209654,
            "content_html": "",
            "url": "https://finance.sina.cn/7x24/2021-06-16/detail-ikqcfnca1310969.d.html",
            "title": "【鱼粉价格涨至一年来高点】中国的养猪饲料用鱼粉需求正在增加，而鱼粉原料鳀鱼的最大生产国秘鲁本年度的捕捞量配额低于市场预期，供求变得紧张。秘鲁产鱼粉价格（高档品）目前为每吨约1650美元。比2020年底上涨约155美元（10％），与2020年7月的近期低点相比上涨255美元（18％）。日本国内的鱼粉也时隔约1年半涨价，东京地区的批发价目前为每吨19.5万日元，比4月上涨约1万日元（5％）。（日经新闻）",
            "date_modified": "2021-06-16T03:14:44.000Z"
        },
        {
            "id": 2209653,
            "content_html": "",
            "url": "https://finance.sina.cn/7x24/2021-06-16/detail-ikqcfnca1310806.d.html",
            "title": "港股医药板块跌幅扩大，中国中药跌7.7%，歌礼制药跌5.9%，复星医药跌5.2%，石药集团跌3.8%。",
            "date_modified": "2021-06-16T03:14:04.000Z"
        },
        {
            "id": 2209652,
            "content_html": "",
            "url": "https://finance.sina.cn/7x24/2021-06-16/detail-ikqcfnca1310774.d.html",
            "title": "  【佛山一封控小区超市哄抬物价被罚十万】6月11日，广东佛山桂城监管所将依法处罚哄抬物价商家。此前，群众反映同成社区某超市哄抬物价，涉嫌违法。经立案调查，监管部门拟依法对该商家处以10万元行政罚款。  （澎湃）",
            "date_modified": "2021-06-16T03:13:58.000Z"
        },
        {
            "id": 2209651,
            "content_html": "",
            "title": "  【东风汽车被执行超8300万 涉及买卖合同纠纷】天眼查App显示，6月15日，东风汽车股份有限公司新增一则被执行人信息，案号为（2021）浙07执503号，执行标的83263360元，执行法院为金华市中级人民法院。相关案件涉及浙江物产中大供应链服务有限公司与东风汽车股份有限公司相关买卖合同纠纷。",
            "date_modified": "2021-06-16T03:12:38.000Z"
        },
        {
            "id": 2209649,
            "content_html": "",
            "url": "https://finance.sina.cn/7x24/2021-06-16/detail-ikqcfnca1309465.d.html",
            "title": "广州白云区：解封不解控，继续禁止人群聚集和堂食。（羊城派）",
            "date_modified": "2021-06-16T03:09:21.000Z"
        },
        {
            "id": 2209646,
            "content_html": "",
            "url": "https://finance.sina.cn/7x24/2021-06-16/detail-ikqcfnca1308187.d.html",
            "title": "  【3位航天员在玻璃房内接受采访 还有小讲台！】神舟十二号载人飞行任务航天员见面会上，航天员聂海胜刘伯明汤洪波与媒体记者见面。他们实行三级医学隔离（最高级别隔离防护），几次载人航天都是如此。与以往不同的是，此次见面会，航天员由“坐着”改为“站着”接受采访。（央视）",
            "date_modified": "2021-06-16T03:04:18.000Z"
        },
        {
            "id": 2209643,
            "content_html": "",
            "url": "https://finance.sina.cn/7x24/2021-06-16/detail-ikqciyzi9905321.d.html",
            "title": "中国信通院：从2021年前五个月的数据来看，国内手机市场保持快速增长，整体呈现上升趋势，其中5G手机实现大幅度增长。",
            "date_modified": "2021-06-16T03:00:40.000Z"
        },
        {
            "id": 2209642,
            "content_html": "",
            "url": "https://finance.sina.cn/7x24/2021-06-16/detail-ikqcfnca1306984.d.html",
            "title": "中国信通院：2021年5月，国内市场5G手机出货量1670万部，占同期手机出货量的72.9%。",
            "date_modified": "2021-06-16T03:00:08.000Z"
        },
        {
            "id": 2209641,
            "content_html": "",
            "url": "https://finance.sina.cn/7x24/2021-06-16/detail-ikqcfnca1306929.d.html",
            "title": "  【神舟十二号载人飞行任务航天员见面会】6月16日，经空间站阶段飞行任务总指挥部研究决定，聂海胜、刘伯明和汤洪波3名航天员将执行神舟十二号载人飞行任务。16日11时，将举行神舟十二号载人飞行任务航天员见面会，3名航天员将与大家见面，并回答记者提问。",
            "date_modified": "2021-06-16T02:59:52.000Z"
        },
        {
            "id": 2209639,
            "content_html": "",
            "url": "https://finance.sina.cn/7x24/2021-06-16/detail-ikqciyzi9904784.d.html",
            "title": "【媒体称台将提出希望与美国签署“台美双边贸易协定” 国台办回应】有记者问，美国贸易代表办公室日前发表新闻稿，美台将恢复“台美贸易暨投资架构协议（TIFA）”商谈。有媒体称，台将提出希望与美国签署“台美双边贸易协定（BTA）”，对此发言人有何评论？马晓光表示，我们坚决反对美国与台湾地区谈判和签订任何具有主权意涵的协议。民进党当局“倚美谋独”，不惜进口“莱猪”，频频出卖岛内民众利益。可以想像，民进党当局为一党私利，只会继续损害广大台湾同胞的利益福祉。（界面）",
            "date_modified": "2021-06-16T02:58:05.000Z"
        },
        {
            "id": 2209636,
            "content_html": "",
            "url": "https://finance.sina.cn/7x24/2021-06-16/detail-ikqciyzi9904424.d.html",
            "title": "  【河北省科技厅与上海证券交易所研究推进科技企业上市服务有关工作】近日，上海证券交易所卢大彪副总经理一行5人到省科技厅对接科技型企业上市服务工作。河北省科技厅李丛民副厅长出席座谈会。卢大彪表示，双方围绕支持科技型企业发展建立了稳定密切合作关系，在开展融资政策宣传、提供上市服务等领域取得明显成效。下一步，希望在共建科创上市企业培育库、共办科创板上市培训班、组织企业“走进上交所”活动等方面进一步深化合作，为更多科技型企业提供优质融资服务。",
            "date_modified": "2021-06-16T02:56:20.000Z"
        },
        {
            "id": 2209635,
            "content_html": "",
            "url": "https://finance.sina.cn/7x24/2021-06-16/detail-ikqcfnca1306069.d.html",
            "title": "沪深两市成交额突破5000亿。",
            "date_modified": "2021-06-16T02:55:40.000Z"
        },
        {
            "id": 2209634,
            "content_html": "",
            "url": "https://finance.sina.cn/7x24/2021-06-16/detail-ikqciyzi9904271.d.html",
            "title": "  【NEC首次接到日本以外的5G基站订单】日本NEC于6月15日发布消息称，从英国大型通信运营商沃达丰集团（Vodafone Group）接到了面向高速通信标准“5G”基站产品的订单。将参与沃达丰与韩国三星电子及美国戴尔科技等推进的采用“Open-RAN”技术的通信网构建计划。",
            "date_modified": "2021-06-16T02:55:29.000Z"
        },
        {
            "id": 2209633,
            "content_html": "",
            "url": "https://finance.sina.cn/7x24/2021-06-16/detail-ikqciyzi9903752.d.html",
            "title": "【河北省委书记：北京企业转移雄安新区累计注册3756家】中共河北省委书记、省人大常委会主任王东峰介绍，雄安新区稳妥有序承接北京疏解的存量和增量，截至目前，北京企业转移雄安新区累计注册3756家，首家央企中国卫星网络集团有限公司注册落户新区，雄安新区从规划建设为主，进入承接北京非首都功能疏解和建设同步推进的重要阶段。（新京报）",
            "date_modified": "2021-06-16T02:53:09.000Z"
        },
        {
            "id": 2209632,
            "content_html": "",
            "url": "https://finance.sina.cn/7x24/2021-06-16/detail-ikqcfnca1305010.d.html",
            "title": "  【蚂蚁入股易维科技 后者为健康医疗创新应用服务公司】天眼查App显示，近日，易联众易维科技有限公司发生多项工商变更，新增股东蚂蚁关联公司北京云慧联信息技术有限公司，注册资本由5000万元人民币增至约5357万元人民币，增幅约7.14%。官网信息显示，易联众易维科技有限公司（简称易维科技）是一家专注于医疗保障及健康医疗创新应用服务相关领域的公司。",
            "date_modified": "2021-06-16T02:51:11.000Z"
        },
        {
            "id": 2209631,
            "content_html": "",
            "title": "广州：虽然昨日零新增，仍不排除有散发病例风险，仍要全力排查、严防严守。（南方Plus）",
            "date_modified": "2021-06-16T02:49:24.000Z"
        },
        {
            "id": 2209629,
            "content_html": "",
            "url": "https://finance.sina.cn/7x24/2021-06-16/detail-ikqcfnca1303276.d.html",
            "title": "  【小米投资黑鲨科技公开AI性能增强专利】天眼查App显示，近日，小米投资控股的南昌黑鲨科技有限公司公开了“一种用于增强智能终端的AI性能的方法及系统”专利，公开号为CN112965922A，申请日期为2021年3月3日。专利摘要显示，该发明通过独立的所述AI处理芯片承担智能终端的大部分AI增强任务，可实现游戏或视频等的低画质增强、低帧率插帧，提供高分辨率、高帧率的游戏和视频效果，该AI处理芯片内置图像融合模块，通过显示模块实时显示，不需回传到SOC芯片，可实现超低延时，提升用户体验。",
            "date_modified": "2021-06-16T02:44:10.000Z"
        },
        {
            "id": 2209628,
            "content_html": "",
            "url": "https://finance.sina.cn/7x24/2021-06-16/detail-ikqcfnca1303104.d.html",
            "title": "  【华为注册手译商标】天眼查App显示，近日，华为技术有限公司申请注册多个“华为手译”商标，国际分类涉及教育娱乐、网站服务等，当前商标状态为“商标申请中”。",
            "date_modified": "2021-06-16T02:43:28.000Z"
        },
        {
            "id": 2209625,
            "content_html": "",
            "url": "https://finance.sina.cn/7x24/2021-06-16/detail-ikqcfnca1301814.d.html",
            "title": "A股汽车板块跌幅进一步扩大，海马汽车跌停，北汽蓝谷大跌超8%，长城汽车跌超7%，长安汽车、东风汽车、江淮汽车等纷纷下挫。港股方面，长城汽车大跌近8%，比亚迪股份跌近5%、广汽集团、吉利汽车等跟跌。",
            "date_modified": "2021-06-16T02:38:53.000Z"
        },
        {
            "id": 2209624,
            "content_html": "",
            "url": "https://finance.sina.cn/7x24/2021-06-16/detail-ikqcfnca1301629.d.html",
            "title": "  【美方吹风美俄领导人会晤议程 “明确”三项预期】美国政府高级别官员15日表示，美方不期待美俄领导人日内瓦会晤取得成果，但寻求达成三项“基本目标”。一是明确美俄双方可以合作促进彼此国家利益和全球安全的一系列任务。二是向俄方明确涉及美国国家利益的重要领域。在这些领域，俄方与其利益相悖的活动将遭到回应。三是明确阐述拜登对“美国价值观和优先事项”的愿景。（中新社）",
            "date_modified": "2021-06-16T02:38:02.000Z"
        },
        {
            "id": 2209623,
            "content_html": "",
            "title": "  【欧洲首台量子计算机在德国斯图加特揭幕】当地时间15日，欧洲首台量子计算机在德国斯图加特附近正式揭幕。这款商用量子计算机在投入使用后也将造福工业界。",
            "date_modified": "2021-06-16T02:37:36.000Z"
        },
        {
            "id": 2209619,
            "content_html": "",
            "url": "https://finance.sina.cn/7x24/2021-06-16/detail-ikqcfnca1300798.d.html",
            "title": "【国务院教育督导委员会办公室提示校外培训风险：缴费套路多，警惕勿上当】学期考试临近、暑假将至，国务院教育督导委员会办公室提醒广大家长，在为孩子选择培训项目、缴纳培训费用时，特别注意以下事项：一、警惕虚假宣传诱导缴费。二、警惕巧立名目违规收费。对超出公示范围、一次性超过3个月或60课时的收费，需仔细辨别，谨慎操作。三、警惕炮制噱头高额收费。请家长朋友们擦亮眼睛，避免上当受骗。如果遇以上行为，要及时向当地市场监管部门或教育行政部门反映，以维护自身权益。",
            "date_modified": "2021-06-16T02:34:19.000Z"
        },
        {
            "id": 2209618,
            "content_html": "",
            "url": "https://finance.sina.cn/7x24/2021-06-16/detail-ikqciyzi9898930.d.html",
            "title": "  【东北能源监管局：把握好煤电机组发展和引导退出的节奏 配合好专项监管工作开展和发现问题的整改落实】东北能源监管局于6月10日-15日期间分省召开了东北地区煤电淘汰落后产能专项监管工作座谈会。郭建宇副局长参加了会议并就此次监管工作和未来一段时期东北煤电淘汰落后产能和规划建设工作强调了三点意见。一是正确认识煤电淘汰落后产能和规划建设工作的重要意义，二是把握好煤电机组发展和引导退出的节奏，三是配合好专项监管工作开展和发现问题的整改落实。",
            "date_modified": "2021-06-16T02:33:56.000Z"
        },
        {
            "id": 2209616,
            "content_html": "",
            "url": "https://finance.sina.cn/7x24/2021-06-16/detail-ikqciyzi9898650.d.html",
            "title": "CRO板块个股集体调整，康龙化成大跌5%，昭衍新药、凯莱英、药明康德、泰格医药等个股均跌超4%。",
            "date_modified": "2021-06-16T02:32:32.000Z"
        }
    ]
}