{
    "version": "https://jsonfeed.org/version/1",
    "title": "新浪新闻",
    "home_page_url": "https://tk14.github.io/sina-news/",
    "feed_url": "https://tk14.github.io/sina-news/rss.json",
    "description": "新浪全球实时财经新闻直播",
    "items": [
        {
            "id": 3236128,
            "content_html": "",
            "url": "https://finance.sina.cn/7x24/2023-09-09/detail-imzmamrn4791477.d.html",
            "title": "国家统计局：2023年8月份，全国工业生产者出厂价格同比下降3.0%，环比上涨0.2%；工业生产者购进价格同比下降4.6%，环比上涨0.2%。1—8月平均，工业生产者出厂价格比上年同期下降3.2%，工业生产者购进价格下降3.6%。",
            "date_modified": "2023-09-09T01:32:31.000Z"
        },
        {
            "id": 3236126,
            "content_html": "",
            "title": "国家统计局：8月份，全国居民消费价格环比上涨0.3%。其中，城市上涨0.2%，农村上涨0.4%；食品价格上涨0.5%，非食品价格上涨0.2%；消费品价格上涨0.4%，服务价格上涨0.1%。",
            "date_modified": "2023-09-09T01:32:04.000Z"
        },
        {
            "id": 3236124,
            "content_html": "",
            "title": "国家统计局：2023年8月份，全国居民消费价格同比上涨0.1%。其中，城市上涨0.2%，农村下降0.2%；食品价格下降1.7%，非食品价格上涨0.5%；消费品价格下降0.7%，服务价格上涨1.3%。1­­—8月平均，全国居民消费价格比上年同期上涨0.5%",
            "date_modified": "2023-09-09T01:31:42.000Z"
        },
        {
            "id": 3236121,
            "content_html": "",
            "url": "https://finance.sina.cn/7x24/2023-09-09/detail-imzmamrn4789407.d.html",
            "title": "【美国伊利诺伊州：国轩高科将斥资20亿美元建电动汽车电池超级工厂】 当地时间9月8日，美国伊利诺伊州政府官网发布声明，宣布国轩高科将斥资20亿美元在该州坎卡基县曼特诺新建电动汽车电池超级工厂，预计将生产10吉瓦时的锂离子电池组和40吉瓦时的锂离子电池芯，计划明年投产。（界面新闻）",
            "date_modified": "2023-09-09T01:21:59.000Z"
        },
        {
            "id": 3236120,
            "content_html": "",
            "url": "https://finance.sina.cn/7x24/2023-09-09/detail-imzmamrn4789191.d.html",
            "title": "【摩洛哥地震已造成至少4人死亡】据当地媒体报道，当地时间8日晚，位于摩洛哥中部的瓦尔扎扎特地区因强烈地震而导致房屋倒塌，已造成4人死亡。 另据报道，遭遇地震后，马拉喀什市至少有20多栋建筑倒塌。（央视）",
            "date_modified": "2023-09-09T01:21:19.000Z"
        },
        {
            "id": 3236119,
            "content_html": "",
            "url": "https://finance.sina.cn/7x24/2023-09-09/detail-imzmamrh6082521.d.html",
            "title": "【对于联发科开始大砍2024年的wafer（晶圆）投片数量的消息，官方予以否认】 9月8日晚间，面对市场传闻，联发科CFO顾大为对第一财经独家表示，公司没有下调出货（数字）。“第三季业绩符合当时给出的guidance（指导）。”顾大为说。（一财）",
            "date_modified": "2023-09-09T01:19:10.000Z"
        },
        {
            "id": 3236118,
            "content_html": "",
            "url": "https://finance.sina.cn/7x24/2023-09-09/detail-imzmamrk1405036.d.html",
            "title": "【光刻机巨头CEO：孤立中国没有希望】“完全孤立中国是没有希望的。如果我们不分享技术，他们就会自己去研究。”日前，荷兰光刻机巨头阿斯麦（ASML）CEO温宁克（Peter Wennink）在当地电视节目Nieuwsuur上说道。“中国有14亿人，其中很多人都很聪明。他们会提出我们还没想到的解决方案。你在迫使他们变得非常创新。”温宁克认为，试图通过禁止技术移民和出口管制等方式孤立中国，实际上会削弱西方自己。（环球时报）",
            "date_modified": "2023-09-09T01:16:39.000Z"
        },
        {
            "id": 3236117,
            "content_html": "",
            "url": "https://finance.sina.cn/7x24/2023-09-09/detail-imzmamrq1565209.d.html",
            "title": "【辰安科技：中标珠海高新区应急管理局项目】 近日，辰安科技中标珠海高新区应急管理局应急指挥综合建设项目——高新区城市安全风险监测预警平台及区应急指挥中心建设项目（城市安全风险监测预警平台）。此前，辰安科技曾中标珠海市三防指挥系统二期工程（应急部分），此次中标的项目将在原有项目建设基础上深度拓展延伸，通过城市安全风险监测预警平台建设，实现珠海高新区城市安全管理模式的转变。",
            "date_modified": "2023-09-09T01:16:24.000Z"
        },
        {
            "id": 3236115,
            "content_html": "",
            "url": "https://finance.sina.cn/7x24/2023-09-09/detail-imzmamrn4787290.d.html",
            "title": "【门头沟区发布地质灾害气象风险黄色预警，这些地区风险较高】市规划自然资源委门头沟分局联合区气象局发布地质灾害气象风险预警：未来24小时，门头沟区清水镇、斋堂镇、雁翅镇、妙峰山镇、王平镇、大台街道、潭柘寺镇、东辛房街道、龙泉镇、城子街道、大峪街道、永定镇、军庄镇发生滑坡、崩塌、泥石流、地面塌陷等地质灾害的风险较高，特发布地质灾害气象风险黄色预警。请注意防范。(北京日报)",
            "date_modified": "2023-09-09T01:12:31.000Z"
        },
        {
            "id": 3236114,
            "content_html": "",
            "title": "【俄罗斯外交部召见亚美尼亚驻俄大使】据央视新闻，当地时间9月8日，俄罗斯外交部发布消息称，在近期亚美尼亚一系列不友好行为的背景下，俄罗斯外交部召见了亚美尼亚驻俄罗斯大使，向其递交照会，就亚美尼亚国民会议主席西蒙尼扬针对俄外交部发言人扎哈罗娃的言论表达抗议。此前，西蒙尼扬曾在发言中称扎哈罗娃是“某种秘书”。此外，在召见中，俄方还提及了亚美尼亚与美国举行军演、亚美尼亚总理夫人访问基辅等事件。",
            "date_modified": "2023-09-09T01:12:13.000Z"
        },
        {
            "id": 3236113,
            "content_html": "",
            "title": "【华为启动2024届应届生全球招聘】9月9日，据华为招聘官微，华为已启动2024届应届生全球招聘，已开通简历投递通道，提供包括研发、销售、审计、法务、供应链等8个大类岗位，工作地点在深圳、北京、上海、杭州等多个城市。",
            "date_modified": "2023-09-09T01:11:49.000Z"
        },
        {
            "id": 3236112,
            "content_html": "",
            "url": "https://finance.sina.cn/7x24/2023-09-09/detail-imzmamrq1564018.d.html",
            "title": "美国地质勘探局：瓦努阿图伊桑格尔西北以北84公里处发生5.0级地震。",
            "date_modified": "2023-09-09T01:10:53.000Z"
        },
        {
            "id": 3236110,
            "content_html": "",
            "url": "https://finance.sina.cn/7x24/2023-09-09/detail-imzmamrn4785973.d.html",
            "title": "【住建部：真正实施限购的城市还是少数 其中多数对限购进行了优化调整】住房和城乡建设部政策研究中心副主任浦湛表示，随着我国房地产市场供求关系发生重大变化，在因城施策的调控机制下，地方需要根据自身房地产市场形势的变化，进行政策的优化调整。根据我们对这一轮房地产市场调控政策的统计来看，有180多个城市因城施策进行了政策措施的调整，累计调整次数达到了350余次。对于限购政策的调整，我想大家也都很关心，实际上真正实施限购的城市数量还是少数，在少数城市当中，在这一轮房地产市场发展过程当中，也多数对限购进行了优化调整，比如说调整了限购的区域，调整了限购的年限。 (央视新闻)",
            "date_modified": "2023-09-09T01:07:11.000Z"
        },
        {
            "id": 3236109,
            "content_html": "",
            "url": "https://finance.sina.cn/7x24/2023-09-09/detail-imzmamrq1561863.d.html",
            "title": "【X（推特）被抓包：未标注广告内容标签】9 月 9 日消息，部分网友在使用 X（推特）平台时发现，部分广告内容并未正确标注，导致其看起来像是常规内容，在不细查下很难分辨。注：美国的联邦贸易委员会（FTC）和欧盟的欧洲广告标准局（EASA）等机构对广告标签都有严苛要求，无论 X 是偶然还是故意的，都违反了相关法规。（IT之家）",
            "date_modified": "2023-09-09T01:01:34.000Z"
        },
        {
            "id": 3236108,
            "content_html": "",
            "url": "https://finance.sina.cn/7x24/2023-09-09/detail-imzmamrn4782905.d.html",
            "title": "【电气风电与苏交控如东风电签署标杆风场创建协议】9月7日，电气风电与江苏云杉清洁能源投资控股有限公司旗下苏交控如东海上风力发电有限公司（简称“苏交控如东风电”）正式签署苏交控如海风电标杆风场创建协议。双方将以此次标杆风场创建协议签署为契机，进一步深化和推进双方战略合作关系，共同打造海上风电新标杆。",
            "date_modified": "2023-09-09T00:51:48.000Z"
        },
        {
            "id": 3236107,
            "content_html": "",
            "url": "https://finance.sina.cn/7x24/2023-09-09/detail-imzmamrq1559831.d.html",
            "title": "【支持企业纾困，前7月新增减税降费及退税缓费逾万亿】最新数据显示，前7月，全国新增减税降费以及退税缓费1.05万亿元。今年以来，我国聚焦支持做强做优实体经济、促增收扩消费、推动高水平科技自立自强、支持战略性新兴产业发展等多方面举措，打出一套税费政策组合拳，实打实支持企业纾困发展。（经济日报）",
            "date_modified": "2023-09-09T00:51:06.000Z"
        },
        {
            "id": 3236106,
            "content_html": "",
            "url": "https://finance.sina.cn/7x24/2023-09-09/detail-imzmamrq1559690.d.html",
            "title": "【美国夏威夷州州长：仍有66人因毛伊岛大火失踪】美国夏威夷州州长格林当地时间9月8日表示，仍有66人因夏威夷毛伊岛大火失踪，确认死亡人数仍为115人。此外，格林称，从10月8日开始，西毛伊岛的旅行限制将结束，并将重新向游客开放。 (央视新闻)",
            "date_modified": "2023-09-09T00:50:38.000Z"
        },
        {
            "id": 3236105,
            "content_html": "",
            "title": "【每日科技要闻速递（9月9日）】\n新能源汽车要闻：\n1. 特斯拉宣布全球超充桩数量突破5万。\n2. 吉利领克08上市，售价区间为20.88万元-28.80万元。\n集成电路（芯片）要闻\n1. 联发科8月营收422.6亿元新台币，同比减少5.47%。\n2. 台积电8月营收约1886.9亿元新台币：环比增长6.2%，同比下降13.5%。\n人工智能：\n1. 蚂蚁发布金融大模型产品“支小宝”与“支小助”。\n2. 淘宝AI大模型“淘宝问问”正在内测，输入信息生成文字、图片、视频等。\n3. 工信部等五部门印发《元宇宙产业创新发展三年行动计划（2023-2025年）》。\n4. 抖音：发布AI生成、虚构情节等特定内容需主动添加标识，否则最高封号。\n5. 微软CFO预测，微软的AI业务营收将以整个行业史上最快的速度达到100亿美元规模。\n6. 《时代》周刊首次评选全球百大AI人物：马斯克、李彦宏、黄仁勋、Open AI CEO萨姆·奥特曼等获评全球AI领袖。\n其他：\n1. 据英国金融时报：软银旗下芯片设计公司Arm的IPO已获得超额认购逾五倍。\n2. 华为推出Mate60 Pro+及Mate X5折叠屏手机，Mate X5系列上线后秒光。\n3. 传阿里巴巴暂时搁置盒马IPO，盒马方面回应称不予置评。",
            "date_modified": "2023-09-09T00:49:04.000Z"
        },
        {
            "id": 3236104,
            "content_html": "",
            "url": "https://finance.sina.cn/7x24/2023-09-09/detail-imzmamrn4781653.d.html",
            "title": "中央气象台：华南南部强降雨持续，华北部分地区有大到暴雨。",
            "date_modified": "2023-09-09T00:47:13.000Z"
        },
        {
            "id": 3236103,
            "content_html": "",
            "url": "https://finance.sina.cn/7x24/2023-09-09/detail-imzmafiq4911099.d.html",
            "title": "【山东海化集团与泰安市岱岳区签约制盐及储能项目】9月6日，2023中国泰安投资贸易合作洽谈会举行，山东海化集团与泰安市岱岳区签约制盐及储能项目。据悉，此次海化集团与岱岳区签约制盐及储能项目建设地点位于岱岳区马庄镇，由海化集团投资建设。项目计划参与开发马庄镇的岩盐资源，配套建设精制工业盐生产基地，后期利用盐穴建设储气储能产业，配套建设以岩盐资源开发为基础的盐化工产业链，培育绿色低碳产业集群。",
            "date_modified": "2023-09-09T00:41:37.000Z"
        },
        {
            "id": 3236102,
            "content_html": "",
            "url": "https://finance.sina.cn/7x24/2023-09-09/detail-imzmafiq4910190.d.html",
            "title": "【16个受灾地区保险预赔付金额达75.82亿元】记者今天从国家金融监督管理总局了解到，自7月底灾情发生以来，金融监管总局第一时间部署16个受灾地区启动重大灾害应急处置机制，通过主要负责同志牵头开展现场督导、召开专题会议研究推进、印发通知明确提出赔付预赔付目标、持续开展数据监测、不断创新工作方式方法等举措，全面加强统筹指导。截至目前，16个受灾地区保险机构整体赔付预赔付金额达75.82亿元，进度比例超七成，金融支持灾后恢复重建各项工作正有序推进，受灾群众获得感明显增强。金融监管总局相关司局负责人表示，将指导保险业继续高效、细致、专业做好保险理赔服务，同时加强重点受灾地区、重点行业信贷支持力度，优化受灾地区群众信贷服务，合力帮助受灾群众和经营主体渡过难关，尽快恢复灾区生产生活秩序，要协助地方政府把党中央的关心和温暖第一时间传递到灾区，充分体现金融工作的政治性和人民性，发挥好经济“减震器”和社会“稳定器”的功能作用。这位负责人表示，下一步，金融监管总局将继续坚决扛起政治责任，突出重点、细化举措，强化重点领域金融服务，着力提升理赔质效，慎终如始做好防汛救灾各项工作。（央视）",
            "date_modified": "2023-09-09T00:36:52.000Z"
        },
        {
            "id": 3236101,
            "content_html": "",
            "url": "https://finance.sina.cn/7x24/2023-09-09/detail-imzmafiq4909859.d.html",
            "title": "根据阿拉伯电视台援引当地消息人士报道，摩洛哥地震导致5人死亡。",
            "date_modified": "2023-09-09T00:34:52.000Z"
        },
        {
            "id": 3236100,
            "content_html": "",
            "url": "https://finance.sina.cn/7x24/2023-09-09/detail-imzmafiq4908930.d.html",
            "title": "【多地楼市成交量明显放大 政策持续优化】近期，出台楼市优化政策的城市持续增多。受多重政策利好影响，北京、上海等地楼市成交量明显放大。以北京地区为例，记者从中原地产研究院了解到，9月2日、9月3日两天，北京二手房共成交2600套，成交量出现翻倍。业内人士表示，购房者入市积极性明显提升，政策对市场的带动效果正在显现。随着“金九银十”旺季来临，楼市销售有望进一步企稳。（中国证券报）",
            "date_modified": "2023-09-09T00:31:56.000Z"
        },
        {
            "id": 3236099,
            "content_html": "",
            "url": "https://finance.sina.cn/7x24/2023-09-09/detail-imzmafis1685978.d.html",
            "title": "【四大一线城市全部加入“认房不认贷”行列 影响何在？】住房和城乡建设部政策研究中心副主任浦湛：国家层面出台了“认房不认贷”的政策以后，北上广深四个一线城市积极在落地，已经全面落实了“认房不认贷”的政策。从过去房地产市场发展的过程来看，四个一线城市其实都是房地产的热点城市，它们对周边城市乃至更大区域范围内的城市，甚至是全国，都有非常明显的“风向标”作用。另外我们也要看到，随着房地产市场发展，特别是在目前的发展阶段，城市之间的分化更为显著。2018年开始，我们的房地产调控政策实际上就采取了“因城施策”“一城一策”的调控机制。在这一机制下，城市要结合各自房地产市场的发展情况，来完善优化调整调控政策。（央视新闻）",
            "date_modified": "2023-09-09T00:31:32.000Z"
        },
        {
            "id": 3236097,
            "content_html": "",
            "title": "国家海洋预报：2023年9月9日6时10分（北京时间），摩洛哥（30.78 N,8.61 W）发生6.9级地震，震源深度为10.0千米（震源参数修订）。自然资源部海啸预警中心根据监测数据分析，此次地震没有监测到海啸。",
            "date_modified": "2023-09-09T00:27:58.000Z"
        },
        {
            "id": 3236095,
            "content_html": "",
            "url": "https://finance.sina.cn/7x24/2023-09-09/detail-imzmafis1685272.d.html",
            "title": "【如何看待“认房不认贷”政策出台的背景和时机？住建部回应】住房和城乡建设部政策研究中心副主任浦湛：背景可以从两方面来看。①从房地产市场的发展情况来看，大家都知道今年一季度市场销售明显回暖，受多方面因素影响，4月份以来，市场成交放缓，市场预期也出现转弱的迹象。②从满足居民的住房需求来看，我们现在还处于城镇化快速发展的后半阶段，去年我们国家的城镇化率是65.2%，距离城镇化稳定阶段还有发展空间，相应的刚性需求还是有比较大的增量。另一方面，城市当中有房的群体，也还有着比较大的改善居住条件的需求，所以从满足刚性和改善性需求的角度来看，也是政策出台的重要背景。（央视新闻）",
            "date_modified": "2023-09-09T00:27:25.000Z"
        },
        {
            "id": 3236094,
            "content_html": "",
            "title": "【朝鲜举行国庆75周年民防阅兵活动】为庆祝朝鲜民主主义人民共和国成立75周年，朝鲜当地时间9月8日在首都平壤市中心的金日成广场举行民防阅兵活动。 (央视新闻)",
            "date_modified": "2023-09-09T00:27:00.000Z"
        },
        {
            "id": 3236092,
            "content_html": "",
            "title": "沃尔玛正在考虑收购ChenMed的多数股权，该交易对ChenMed的估值将达到数十亿美元，达成协议可能还需要数周时间。",
            "date_modified": "2023-09-09T00:25:50.000Z"
        },
        {
            "id": 3236091,
            "content_html": "",
            "url": "https://finance.sina.cn/7x24/2023-09-09/detail-imzmafiq4907633.d.html",
            "title": "【存储芯片下行周期有望见底 A股上市公司加速布局】 近期，存储芯片大厂三星、SK海力士、美光公司等陆续控制产能、酝酿提价，受到业界关注。多位业内人士在接受记者采访时表示，存储芯片价格下行周期一般为1年至2年，本轮存储芯片价格下行自2021年年中开始，结合各大厂自去年下半年起陆续下调产能计划，存储芯片下行周期逐渐走向尾声。信息技术高速发展带来数据存储需求不断增长，未来存储芯片市场空间广阔，在行业周期触底之际，A股上市公司竞相布局存储芯片赛道。一方面，加快技术升级提升竞争力，另一方面，积极开拓市场增加市场份额，紧抓行业复苏机遇。（证券日报）",
            "date_modified": "2023-09-09T00:25:08.000Z"
        },
        {
            "id": 3236089,
            "content_html": "",
            "url": "https://finance.sina.cn/7x24/2023-09-09/detail-imzmafik6204260.d.html",
            "title": "【城商行跟进下调存款利率 “特色存款”成揽储新宠】 进入9月，国有行、股份行集体调降定期存款利率，掀起新一轮“降息潮”。北京银行、上海银行、重庆银行、苏州银行等城商行纷纷加入下调存款利率的阵营。业内人士表示，此举在一定程度上有利于银行缓解息差压力。同时，记者走访多家银行网点时发现，不少银行都在推荐“特色存款”。相较于普通定期存款，“特色存款”在利率上颇具优势；相较于大额存单，“特色存款”具有额度优势；此外，“特色存款”的起存金额更为亲民，已成为银行揽储新宠。（中国证券报）",
            "date_modified": "2023-09-09T00:24:41.000Z"
        },
        {
            "id": 3236088,
            "content_html": "",
            "url": "https://finance.sina.cn/7x24/2023-09-09/detail-imzmafin1526808.d.html",
            "title": "【天津市西青区：购买新建商品住宅可给予最高不超过4万元购房补贴】 天津市西青区发布消息称，自2023年9月8日（含当日）至2023年12月31日（含当日），在西青区购买新建商品住宅（以商品房买卖合同网签备案时间为准），且在2023年12月31日（含当日）前足额缴纳购房契税，根据购房人申请，按照总购房款的0.5%给予购房补贴，补贴金额最高不超过4万元（含4万元）。购房人应为自然人，非自然人购房不在补贴范围。（澎湃新闻）",
            "date_modified": "2023-09-09T00:22:46.000Z"
        },
        {
            "id": 3236087,
            "content_html": "",
            "url": "https://finance.sina.cn/7x24/2023-09-09/detail-imzmafiq4907150.d.html",
            "title": "【印尼西努沙登加拉省附近海域发生5.7级地震】据印度尼西亚气象、气候和地球物理局消息，当地时间9月9日7时06分，印尼西努沙登加拉省北龙目县东北139公里处海域发生5.7级地震，震中位于南纬7.19度，东经116.61度，震源深度500公里。预计不会发生海啸。",
            "date_modified": "2023-09-09T00:22:31.000Z"
        },
        {
            "id": 3236086,
            "content_html": "",
            "url": "https://finance.sina.cn/7x24/2023-09-09/detail-imzmafiq4907039.d.html",
            "title": "【广东今天部分地区仍有强降雨 粤西珠三角等地或有大暴雨】广东部分地区9日仍有强降雨，粤西、珠江三角洲局地或有大暴雨。近期广东多地降雨持续待机，局地累计雨量大，需警惕降雨叠加可能导致的山体滑坡、泥石流等次生灾害。受“海葵”残余环流的影响，3日开始，广东多地遭遇强降雨。广东省气象台预计，今天部分地区仍有强降雨，其中粤西市县、珠江三角洲南部市县有大雨到暴雨，局部（特）大暴雨，其余市县多云到阴天，有阵雨。 (央视新闻)",
            "date_modified": "2023-09-09T00:22:00.000Z"
        },
        {
            "id": 3236085,
            "content_html": "",
            "url": "https://finance.sina.cn/7x24/2023-09-09/detail-imzmafis1683460.d.html",
            "title": "【维珍银河完成第三次商业太空飞行】当地时间9月8日，维珍银河控股公司在官网宣布，其第二次私人宇航员飞行任务“银河03”已经完成。此次任务运送了该公司首批客户中的三位。“银河03”是维珍银河在过去四个月中成功进行的第四次太空飞行，也是该公司商业太空飞行首季的第三次飞行。公司将着手进行飞行后检查和分析，为计划于10月初进行的下一次商业太空任务“银河04”做准备。",
            "date_modified": "2023-09-09T00:18:55.000Z"
        },
        {
            "id": 3236084,
            "content_html": "",
            "url": "https://finance.sina.cn/7x24/2023-09-09/detail-imzmafiq4905925.d.html",
            "title": "【房山区所有涉山涉水乡村旅游民宿暂停营业，这些景区临时关闭】按照北京市相关部门要求，9月9日，房山区除首创奥特莱斯休闲驿站外其他旅游景区暂时关闭，所有涉山涉水乡村旅游民宿暂停营业。（北京日报）",
            "date_modified": "2023-09-09T00:14:59.000Z"
        },
        {
            "id": 3236083,
            "content_html": "",
            "url": "https://finance.sina.cn/7x24/2023-09-09/detail-imzmafik6202892.d.html",
            "title": "【30只北交所主题基金斩获正收益 公募称将积极开发相关产品】9月8日，距离《关于高质量建设北京证券交易所的意见》（即“北交所深改19条”，以下简称《意见》）正式发布刚满一周。据东方财富Choice数据统计，截至9月8日，可统计本周以来收益率的30只北交所主题基金和北交所相关指数基金（不同份额分开统计）均斩获正收益。受访公募机构表示，《意见》在多方面发挥有利影响，机构将继续积极布局北交所。（证券日报）",
            "date_modified": "2023-09-09T00:14:13.000Z"
        },
        {
            "id": 3236081,
            "content_html": "",
            "url": "https://finance.sina.cn/7x24/2023-09-09/detail-imzmafis1682241.d.html",
            "title": "【沙砾生物完成4亿元B轮融资，由中金资本旗下基金领投】9月8日，沙砾生物（Grit Biotechnology）通过官微宣布完成4亿元人民币的B轮融资，本轮融资由中金资本旗下基金领投，前海方舟、联东投资、源禾资本、禾方田合伙企业以及老股东夏尔巴投资、德诚资本、经纬中国跟投。本轮融资将用于支持公司肿瘤浸润淋巴细胞（TIL）疗法管线的开发，包括GT101的关键临床试验以及多项下一代基因编辑型TIL管线的开发。",
            "date_modified": "2023-09-09T00:11:09.000Z"
        },
        {
            "id": 3236077,
            "content_html": "",
            "url": "https://finance.sina.cn/7x24/2023-09-09/detail-imzmafiq4903861.d.html",
            "title": "【佛山中研磁电完成增资4000万元】佛山中研磁电科技股份有限公司近日宣布完成增资4000万元，本轮融资由尚颀资本领投。本轮融资资金将用于提升公司流动能力、新工厂建设、产品研发量产以及市场开拓。该公司成立于2008年，是一家研发、生产非晶纳米晶系列产品的新材料企业。",
            "date_modified": "2023-09-09T00:06:50.000Z"
        },
        {
            "id": 3236072,
            "content_html": "",
            "url": "https://finance.sina.cn/7x24/2023-09-09/detail-imzmafiq4902655.d.html",
            "title": "【北上资金流出趋缓 逆势加仓汽车股】 本周，北上资金流出继续趋缓，全周净卖出47.56亿元。其中，沪股通净卖出46.31亿元，深股通仅净卖出1.25亿元。汽车、银行、化工、采掘四行业本周获得北上资金超10亿元净买入，有色金属、家用电器、通信等行业则获得超亿元加仓。券商股继续遭大幅减持，非银金融行业被净卖出逾34亿元，医药生物、传媒被净卖出超20亿元。今年以来，持续不断促消费政策的实施，汽车消费市场呈现复苏态势。",
            "date_modified": "2023-09-09T00:00:34.000Z"
        },
        {
            "id": 3236070,
            "content_html": "",
            "url": "https://finance.sina.cn/7x24/2023-09-09/detail-imzmafis1679240.d.html",
            "title": "【日本千叶县遭遇破纪录暴雨，多地道路及房屋被淹】据日本《东京新闻》当地时间9月9日报道，8日随着第13号台风“鸳鸯”逼近，日本千叶县遭遇破纪录暴雨，造成多地道路及房屋被淹。其中，茂原市等地的12小时降雨量创下有相关气象纪录以来的最大值。据千叶县政府称，截至当地时间8日16时，暂无人员伤亡报告。暴雨导致流经千叶县的7条河流发生溢流。此外，暴雨还导致了千叶县境内约5800户居民停电，多条轨道交通线路一度停运。（央视新闻）",
            "date_modified": "2023-09-08T23:56:18.000Z"
        },
        {
            "id": 3236066,
            "content_html": "",
            "url": "https://finance.sina.cn/7x24/2023-09-09/detail-imzmafiq4900504.d.html",
            "title": "【房山暴雨黄色预警 部分地区地质灾害气象风险黄色预警】房山区气象台2023年9月9日03时35分升级发布暴雨黄色预警信号：预计，当前至9日14时，房山区6小时累计雨量可达70毫米以上，山区及浅山区出现强降水诱发的中小河流洪水、山洪、地质灾害等次生灾害风险较大，城市低洼地区容易出现积水，请注意防范。市规划自然资源委房山分局、房山区气象局2023年9月9日05时联合发布地质灾害气象风险黄色预警。未来24小时，房山区蒲洼乡、霞云岭乡、史家营乡、大安山乡、佛子庄乡、南窖乡、河北镇、十渡镇、张坊镇、大石窝镇、韩村河镇、周口店镇、青龙湖镇、东风街道、城关街道发生崩塌、滑坡、泥石流、地面塌陷等地质灾害的风险较高，特升级发布地质灾害气象风险黄色预警。请注意防范。",
            "date_modified": "2023-09-08T23:45:53.000Z"
        },
        {
            "id": 3236065,
            "content_html": "",
            "url": "https://finance.sina.cn/7x24/2023-09-09/detail-imzmafin1521405.d.html",
            "title": "【安理会就乌克兰局势举行会议，中方呼吁国际社会推动停火止战】据央视新闻，当地时间9月8日，联合国安理会就乌克兰局势举行临时会议。中国常驻联合国副代表耿爽在发言时呼吁国际社会推动停火止战，安理会应发挥作用，推动各类和平倡议的落实，发挥国际集体安全机制核心作用。中方表示，中方在乌克兰问题上的立场是一贯的、明确的，始终认为各国主权、领土完整都应得到维护，《联合国宪章》宗旨和原则都应得到遵守，各方合理安全关切都应得到重视，一切有利于和平解决危机的努力都应得到支持。",
            "date_modified": "2023-09-08T23:43:48.000Z"
        },
        {
            "id": 3236064,
            "content_html": "",
            "url": "https://finance.sina.cn/7x24/2023-09-09/detail-imzmafis1676984.d.html",
            "title": "【中央气象台对台风“鸳鸯”停止编号】今年第13号台风“鸳鸯”已于9月8日下午在日本以南洋面减弱为热带低压，目前其风力进一步减弱，已很难确定其环流中心，中央气象台于9月8日20时对其停止编号。",
            "date_modified": "2023-09-08T23:42:03.000Z"
        },
        {
            "id": 3236061,
            "content_html": "",
            "url": "https://finance.sina.cn/7x24/2023-09-09/detail-imzmafin1521058.d.html",
            "title": "【北京住总集团拟发行不超过10亿元中票，偿还9月17日到期的债务】9月8日，上海清算所披露北京住总集团有限责任公司2023年度第一期中期票据发行文件。根据文件，北京住总集团拟发行不超过10亿元中期票据，拟用于偿还公司到期的债务融资工具。根据募集说明书，计划偿还的债务融资工具为“21京住总集MTN003A”，当前余额为10亿元，到期日为2023年9月17日。",
            "date_modified": "2023-09-08T23:40:52.000Z"
        },
        {
            "id": 3236059,
            "content_html": "",
            "title": "除了头版内容，今天《人民日报》涉及财经的主要内容还包括：\n1、李鸿忠出席朝鲜驻华使馆国庆75周年招待会；\n2、委内瑞拉总统马杜罗 9月8日至14日对中国进行国事访问；\n3、张国清将赴俄罗斯出席第八届东方经济论坛；\n4、外交部发言人就委内瑞拉总统马杜罗将访华介绍有关情况；\n5、赞比亚总统希奇莱马将访华；\n6、外交部发言人：高度赞赏阿盟外长理事会连续第四十三次通过涉华友好决议；\n7、外交部发言人：愿同澳方一道推动中澳全面战略伙伴关系行稳致远；\n8、外交部发言人就赞比亚总统希奇莱马将访华介绍有关情况；\n9、刘建超访问老挝；\n10、各国议会联盟主席将访华；\n11、李强同印度尼西亚总统佐科会谈；\n12、韩正会见委内瑞拉副总统罗德里格斯；\n13、促进双向投资 释放品牌效应——写在第二十三届中国国际投资贸易洽谈会举办之际；\n14、2023年中国农民丰收节金秋消费季在京启动 5届累计带动农产品销售超800亿元；\n15、王勇出席第二十三届中国国际投资贸易洽谈会暨2023国际投资论坛开幕式并致辞；\n16、暴雨致多个地区发生水浸 香港特区政府各部门全力应对；\n17、宋涛会见亲民党主席宋楚瑜。",
            "date_modified": "2023-09-08T23:23:02.000Z"
        },
        {
            "id": 3236057,
            "content_html": "",
            "url": "https://finance.sina.cn/7x24/2023-09-09/detail-imzmafis1673254.d.html",
            "title": "【海航航空集团：7月总体收入已恢复至2019年同期的109%】海航航空集团9月8日晚于官微发布消息称，集团旗下境内航司2023年暑期航班量及旅客运输量涨幅明显，国内航线执行航班量超13.5万班，承运旅客超2030万人次，超过2019年同期水平。另外，据财务数据显示，2023年7月海航航空集团总体收入已恢复至2019年同期的109%。如不考虑汇兑变动，集团已实现2023年1-7月整体盈利。",
            "date_modified": "2023-09-08T23:19:35.000Z"
        },
        {
            "id": 3236055,
            "content_html": "",
            "url": "https://finance.sina.cn/7x24/2023-09-09/detail-imzmafis1672072.d.html",
            "title": "【英伟达再度发力AI 联手两大印度企业开发超算、大模型及应用】英伟达分别和印度最大私营企业信实工业及印度最大企业集团塔塔达成合作，和信实开发印度语言的基础大语言模型，和塔塔开发AI云和AI超级计算机，两家公司都将打造AI计算基础设施和生成式AI应用。",
            "date_modified": "2023-09-08T23:12:40.000Z"
        },
        {
            "id": 3236054,
            "content_html": "",
            "title": "摩根大通：放弃看涨苹果公司的立场，下调苹果公司股价目标至每股230美元（8月曾上调至235美元）。因为对即将发布的新品iPhone 15的预期偏低，预计换新的机主不会有太显著的增长。",
            "date_modified": "2023-09-08T23:11:47.000Z"
        },
        {
            "id": 3236053,
            "content_html": "",
            "title": "【美法官驳回前白宫办公厅主任将佐治亚州大选案件移交联邦法院的请求】根据美国有线电视新闻网的报道，当地时间9月8日，美国一名联邦法官驳回了美国前白宫办公厅主任马克·梅多斯（Mark Meadows）将有关他的“涉嫌推翻美国2020年总统选举佐治亚州结果”案件移交至联邦法院的请求。 (央视新闻)",
            "date_modified": "2023-09-08T23:04:14.000Z"
        },
        {
            "id": 3236051,
            "content_html": "",
            "url": "https://finance.sina.cn/7x24/2023-09-09/detail-imzmafis1669862.d.html",
            "title": "【俄称击退乌军进攻 乌称打击俄军目标】俄罗斯国防部当地时间8日发布战报称，俄军在扎波罗热、顿涅茨克、红利曼、库皮扬斯克方向击退乌军多次进攻。此外，俄军还打击了位于顿涅茨克地区的乌军多个指挥观察所，摧毁了一座武器弹药库。俄军防空系统拦截了4枚火箭弹，击落31架无人机。同一天，乌克兰武装部队总参谋部发布战报称，在过去24小时内，乌军与俄军前线地区发生24次战斗。苏梅、切尔尼戈夫等地遭俄军炮弹及导弹打击。乌军对俄军人力和装备集中区、弹药库等目标进行了打击。",
            "date_modified": "2023-09-08T22:53:12.000Z"
        },
        {
            "id": 3236050,
            "content_html": "",
            "url": "https://finance.sina.cn/7x24/2023-09-09/detail-imzmafis1669675.d.html",
            "title": "  【三亚市发布暴雨橙色预警】三亚市气象台2023年09月09日06时12分发布暴雨橙色预警信号 ：受强对流云团影响，三亚市吉阳区北部和海棠区北部已出现强降雨天气，其中吉阳区三浓水库附近区域过去6小时内降雨量已达853毫米，预计该强对流将向东北方向移动且强度维持，吉阳区北部和海棠区北部的强降雨仍将持续，请注意防范强降雨可能引发的城市内涝、中小河流洪水、山洪和山体滑坡等地质灾害。",
            "date_modified": "2023-09-08T22:51:45.000Z"
        },
        {
            "id": 3236049,
            "content_html": "",
            "url": "https://finance.sina.cn/7x24/2023-09-09/detail-imzmafis1669313.d.html",
            "title": "【引滦入津工程已累计向天津供水约333亿立方米】天津市政府新闻办9月8日召开的新闻发布会上透露，引滦入津工程自1983年9月正式通水以来，已累计向天津安全供水约333亿立方米，有力支撑了城市经济社会发展。",
            "date_modified": "2023-09-08T22:49:29.000Z"
        },
        {
            "id": 3236046,
            "content_html": "",
            "url": "https://finance.sina.cn/7x24/2023-09-09/detail-imzmafis1667178.d.html",
            "title": "【西南航空称发现了一个疑似来自AOG的发动机部件】美国西南航空公司(Southwest Airlines)表示，其供应商在审查后发现，其一架飞机的发动机中含有来自AOG Technics的“可疑部件”，这使其成为第一家公开证实在商用飞机上使用这些部件的主要航空公司。西南航空周五在电子邮件中表示，出于谨慎考虑，这些部件立即被更换。",
            "date_modified": "2023-09-08T22:29:38.000Z"
        },
        {
            "id": 3236045,
            "content_html": "",
            "url": "https://finance.sina.cn/7x24/2023-09-09/detail-imzkzyzs5020272.d.html",
            "title": "【证券日报头版：税费“组合拳”，换来企业创新大实惠】截至目前，相关部门针对科技创新的主要环节和关键领域，陆续推出40多项税费优惠政策，覆盖企业整个生命周期。从企业层面上看，税收优惠有三个作用：一是通过减免企业所得税、增值税或其他税费，可以节约企业成本，提高盈利能力。二是税收优惠可以鼓励企业增加生产投入、扩大生产规模，推动经济增长。三是税收优惠可让企业轻装简行，为初创企业提供更好的资金支持和发展环境，培育新的增长点。综上所述，税收优惠作为一种重要的经济政策，为企业纾困及创新发展带来“大实惠”，将激励企业加快实现高质量发展，有力服务了国家创新驱动发展战略。",
            "date_modified": "2023-09-08T22:22:45.000Z"
        },
        {
            "id": 3236044,
            "content_html": "",
            "title": "【国家疾控局发布秋季儿童轮状病毒感染健康提示】进入秋季，部分家长表示家中孩子出现呕吐、腹泻症状的情况变多，这可能是儿童轮状病毒急性胃肠炎。国家疾控局近日发布健康提示，提醒孩子及其看护人要养成良好卫生习惯，尤其是注意手卫生，不用脏手触摸口、眼、鼻和食物等，不要让幼儿吃手，及时清洁孩子的手，预防秋季儿童轮状病毒感染。中国疾控中心有关专家表示，被感染的儿童，病情一般不会太严重。适当补液，可以“不药而愈”。但当腹泻或呕吐严重时，不可忽视，要及时就医。避免孩子因为脱水严重导致休克，尤其是小于1岁的幼儿。同时，建议家长们注意家庭卫生，室内常通风，孩子们的食具使用前需清洗干净，衣被、玩具等要勤换洗。（新华网）",
            "date_modified": "2023-09-08T22:18:13.000Z"
        },
        {
            "id": 3236043,
            "content_html": "",
            "title": "标普：由于缺乏信息，暂停确认对白俄罗斯的评级。",
            "date_modified": "2023-09-08T22:18:00.000Z"
        },
        {
            "id": 3236041,
            "content_html": "",
            "url": "https://finance.sina.cn/7x24/2023-09-09/detail-imzkzyzu1796674.d.html",
            "title": "【经济日报：发展银发经济要坚持问题导向】近年来，在一系列政策支持下，我国银发经济取得了初步发展。但从目前看，产业发展仍旧总量不够、结构不优、供需不平衡。供给的产品没有及时跟进，质量和服务都有待提高，大量细分需求尚未得到重视和满足，侵害老年消费者合法权益等现象时有发生。让银发经济的消费潜力真正变成发展实力，关键是要坚持问题导向，多方共同发力老人“急难愁盼”的诸多“关键小事”，正是政策的发力点、市场的增长点。要着力解决老年助餐、失能照护等事项，对公共基础设施、居家环境、交通出行、智能应用等加快适老化改造。完善要素支持，培育更多主体，推动银发经济实现规模化、标准化、集群化、品牌化发展。",
            "date_modified": "2023-09-08T22:15:24.000Z"
        },
        {
            "id": 3236040,
            "content_html": "",
            "url": "https://finance.sina.cn/7x24/2023-09-09/detail-imzkzyzs5018253.d.html",
            "title": "天风证券分析师郭明錤：预计标准版iPhone 15是首款采用堆栈CIS的手机。",
            "date_modified": "2023-09-08T22:05:36.000Z"
        },
        {
            "id": 3236039,
            "content_html": "",
            "url": "https://finance.sina.cn/7x24/2023-09-09/detail-imzkzyzs5018101.d.html",
            "title": "【中央气象台9月9日06时继续发布暴雨黄色预警】预计，9月9日08时至10日08时，山西南部、河北中部、北京东南部、天津大部、河南北部和西部、广东中部和西南部、香港、澳门、广西东南部、海南岛、台湾岛等地部分地区有大到暴雨，其中，北京东南部、广西东南部沿海、广东西南部等地部分地区有大暴雨（100～150毫米）。上述部分地区伴有短时强降水（最大小时降雨量20～50毫米，局地可超过70毫米），局地有雷暴大风等强对流天气。",
            "date_modified": "2023-09-08T22:05:03.000Z"
        },
        {
            "id": 3236036,
            "content_html": "",
            "url": "https://finance.sina.cn/7x24/2023-09-09/detail-imzkzyzs5016419.d.html",
            "title": "【深圳气象台：暴雨黄色预警信号持续生效中】深圳市气象台9月9日05时10分发布预报：目前强雷雨云团位于海上，强降雨云团将可能于8时后自南向北影响深圳市，降雨趋于频密。暴雨黄色预警信号持续生效中。",
            "date_modified": "2023-09-08T21:46:41.000Z"
        },
        {
            "id": 3236031,
            "content_html": "",
            "url": "https://finance.sina.cn/7x24/2023-09-09/detail-imzkzyzu1791299.d.html",
            "title": "惠誉：确认土耳其主权信用评级在B，上调展望至稳定（之前持负面展望）。",
            "date_modified": "2023-09-08T21:05:20.000Z"
        },
        {
            "id": 3236029,
            "content_html": "",
            "title": "中国地震台网正式测定：09月09日04时55分在新疆阿克苏地区库车市（北纬41.11度，东经83.62度）发生3.7级地震，震源深度16千米。",
            "date_modified": "2023-09-08T21:03:31.000Z"
        },
        {
            "id": 3236028,
            "content_html": "",
            "url": "https://finance.sina.cn/7x24/2023-09-09/detail-imzkzyzs5013897.d.html",
            "title": "【苹果公司与专利局达成协议，将获得“智能键盘”商标】美国专利与美国商标局（USPTO）将批准苹果公司为“智能键盘”产品申请的两个商标，前提是苹果修改对于该商标所覆盖产品的品类描述。",
            "date_modified": "2023-09-08T20:58:32.000Z"
        }
    ]
}